{"modelRebuildSettings":"{\"categories\":{\"0\":true,\"1\":true,\"2\":true,\"3\":true,\"4\":true},\"docCount\":{\"0\":953,\"1\":513,\"2\":511,\"3\":380,\"4\":436},\"totalDocuments\":2793,\"vocabulary\":{\"0\":true,\"1\":true,\"11\":true,\"12\":true,\"14\":true,\"15\":true,\"25\":true,\"27\":true,\"101\":true,\"102\":true,\"104\":true,\"105\":true,\"107\":true,\"108\":true,\"109\":true,\"111\":true,\"112\":true,\"113\":true,\"114\":true,\"116\":true,\"117\":true,\"118\":true,\"119\":true,\"121\":true,\"123\":true,\"124\":true,\"125\":true,\"126\":true,\"128\":true,\"129\":true,\"131\":true,\"132\":true,\"135\":true,\"136\":true,\"137\":true,\"138\":true,\"139\":true,\"142\":true,\"145\":true,\"146\":true,\"148\":true,\"151\":true,\"156\":true,\"158\":true,\"159\":true,\"161\":true,\"163\":true,\"165\":true,\"166\":true,\"167\":true,\"172\":true,\"174\":true,\"176\":true,\"183\":true,\"185\":true,\"189\":true,\"193\":true,\"194\":true,\"197\":true,\"199\":true,\"205\":true,\"206\":true,\"207\":true,\"208\":true,\"211\":true,\"212\":true,\"219\":true,\"236\":true,\"237\":true,\"242\":true,\"247\":true,\"258\":true,\"302\":true,\"306\":true,\"324\":true,\"335\":true,\"344\":true,\"364\":true,\"387\":true,\"446\":true,\"473\":true,\"935\":true,\"964\":true,\"1001\":true,\"1003\":true,\"1004\":true,\"1005\":true,\"1008\":true,\"1009\":true,\"1011\":true,\"1012\":true,\"1013\":true,\"1014\":true,\"1015\":true,\"1017\":true,\"1018\":true,\"1019\":true,\"1021\":true,\"1022\":true,\"1025\":true,\"1026\":true,\"1027\":true,\"1031\":true,\"1032\":true,\"1033\":true,\"1034\":true,\"1035\":true,\"1037\":true,\"1038\":true,\"1039\":true,\"1042\":true,\"1044\":true,\"1045\":true,\"1047\":true,\"1048\":true,\"1049\":true,\"1051\":true,\"1052\":true,\"1054\":true,\"1055\":true,\"1057\":true,\"1058\":true,\"1059\":true,\"1062\":true,\"1063\":true,\"1064\":true,\"1066\":true,\"1067\":true,\"1068\":true,\"1069\":true,\"1071\":true,\"1072\":true,\"1075\":true,\"1076\":true,\"1077\":true,\"1078\":true,\"1079\":true,\"1081\":true,\"1082\":true,\"1085\":true,\"1087\":true,\"1088\":true,\"1091\":true,\"1092\":true,\"1094\":true,\"1095\":true,\"1096\":true,\"1097\":true,\"1098\":true,\"1099\":true,\"1103\":true,\"1104\":true,\"1105\":true,\"1106\":true,\"1107\":true,\"1108\":true,\"1111\":true,\"1112\":true,\"1114\":true,\"1115\":true,\"1116\":true,\"1117\":true,\"1118\":true,\"1119\":true,\"1121\":true,\"1122\":true,\"1123\":true,\"1124\":true,\"1125\":true,\"1126\":true,\"1127\":true,\"1128\":true,\"1129\":true,\"1133\":true,\"1134\":true,\"1135\":true,\"1137\":true,\"1139\":true,\"1141\":true,\"1142\":true,\"1143\":true,\"1145\":true,\"1146\":true,\"1147\":true,\"1148\":true,\"1149\":true,\"1151\":true,\"1152\":true,\"1153\":true,\"1154\":true,\"1155\":true,\"1156\":true,\"1158\":true,\"1159\":true,\"1161\":true,\"1163\":true,\"1164\":true,\"1167\":true,\"1171\":true,\"1173\":true,\"1174\":true,\"1175\":true,\"1176\":true,\"1177\":true,\"1178\":true,\"1179\":true,\"1181\":true,\"1182\":true,\"1183\":true,\"1185\":true,\"1186\":true,\"1187\":true,\"1188\":true,\"1191\":true,\"1192\":true,\"1193\":true,\"1194\":true,\"1195\":true,\"1196\":true,\"1197\":true,\"1198\":true,\"1199\":true,\"1201\":true,\"1202\":true,\"1203\":true,\"1204\":true,\"1205\":true,\"1207\":true,\"1208\":true,\"1209\":true,\"1211\":true,\"1212\":true,\"1214\":true,\"1215\":true,\"1217\":true,\"1218\":true,\"1219\":true,\"1221\":true,\"1223\":true,\"1224\":true,\"1225\":true,\"1227\":true,\"1229\":true,\"1231\":true,\"1232\":true,\"1233\":true,\"1238\":true,\"1241\":true,\"1242\":true,\"1243\":true,\"1244\":true,\"1245\":true,\"1247\":true,\"1248\":true,\"1249\":true,\"1251\":true,\"1252\":true,\"1255\":true,\"1257\":true,\"1258\":true,\"1259\":true,\"1261\":true,\"1262\":true,\"1263\":true,\"1264\":true,\"1265\":true,\"1266\":true,\"1267\":true,\"1269\":true,\"1271\":true,\"1273\":true,\"1274\":true,\"1278\":true,\"1279\":true,\"1281\":true,\"1282\":true,\"1283\":true,\"1287\":true,\"1289\":true,\"1291\":true,\"1292\":true,\"1295\":true,\"1297\":true,\"1302\":true,\"1303\":true,\"1305\":true,\"1307\":true,\"1308\":true,\"1314\":true,\"1315\":true,\"1316\":true,\"1318\":true,\"1319\":true,\"1322\":true,\"1325\":true,\"1326\":true,\"1327\":true,\"1329\":true,\"1332\":true,\"1335\":true,\"1338\":true,\"1341\":true,\"1342\":true,\"1344\":true,\"1345\":true,\"1348\":true,\"1349\":true,\"1351\":true,\"1353\":true,\"1354\":true,\"1357\":true,\"1358\":true,\"1361\":true,\"1363\":true,\"1364\":true,\"1367\":true,\"1368\":true,\"1369\":true,\"1372\":true,\"1373\":true,\"1375\":true,\"1377\":true,\"1378\":true,\"1381\":true,\"1383\":true,\"1384\":true,\"1386\":true,\"1388\":true,\"1391\":true,\"1393\":true,\"1394\":true,\"1395\":true,\"1396\":true,\"1398\":true,\"1401\":true,\"1403\":true,\"1405\":true,\"1406\":true,\"1408\":true,\"1409\":true,\"1413\":true,\"1415\":true,\"1416\":true,\"1418\":true,\"1422\":true,\"1425\":true,\"1426\":true,\"1429\":true,\"1431\":true,\"1435\":true,\"1438\":true,\"1446\":true,\"1448\":true,\"1449\":true,\"1451\":true,\"1453\":true,\"1454\":true,\"1456\":true,\"1457\":true,\"1461\":true,\"1463\":true,\"1464\":true,\"1466\":true,\"1468\":true,\"1471\":true,\"1472\":true,\"1473\":true,\"1474\":true,\"1475\":true,\"1476\":true,\"1477\":true,\"1478\":true,\"1479\":true,\"1481\":true,\"1482\":true,\"1484\":true,\"1487\":true,\"1491\":true,\"1497\":true,\"1498\":true,\"1499\":true,\"1502\":true,\"1504\":true,\"1506\":true,\"1508\":true,\"1509\":true,\"1514\":true,\"1515\":true,\"1518\":true,\"1519\":true,\"1521\":true,\"1523\":true,\"1525\":true,\"1526\":true,\"1527\":true,\"1528\":true,\"1531\":true,\"1532\":true,\"1533\":true,\"1535\":true,\"1536\":true,\"1538\":true,\"1539\":true,\"1541\":true,\"1545\":true,\"1546\":true,\"1549\":true,\"1551\":true,\"1553\":true,\"1554\":true,\"1555\":true,\"1556\":true,\"1562\":true,\"1564\":true,\"1567\":true,\"1569\":true,\"1571\":true,\"1579\":true,\"1581\":true,\"1582\":true,\"1583\":true,\"1592\":true,\"1594\":true,\"1595\":true,\"1596\":true,\"1599\":true,\"1602\":true,\"1605\":true,\"1607\":true,\"1613\":true,\"1614\":true,\"1616\":true,\"1618\":true,\"1626\":true,\"1632\":true,\"1635\":true,\"1638\":true,\"1639\":true,\"1642\":true,\"1643\":true,\"1644\":true,\"1646\":true,\"1648\":true,\"1652\":true,\"1655\":true,\"1657\":true,\"1665\":true,\"1666\":true,\"1668\":true,\"1671\":true,\"1672\":true,\"1674\":true,\"1675\":true,\"1678\":true,\"1679\":true,\"1683\":true,\"1684\":true,\"1685\":true,\"1687\":true,\"1688\":true,\"1691\":true,\"1693\":true,\"1694\":true,\"1697\":true,\"1699\":true,\"1701\":true,\"1702\":true,\"1711\":true,\"1713\":true,\"1715\":true,\"1717\":true,\"1719\":true,\"1721\":true,\"1723\":true,\"1725\":true,\"1726\":true,\"1731\":true,\"1733\":true,\"1744\":true,\"1748\":true,\"1751\":true,\"1752\":true,\"1756\":true,\"1762\":true,\"1763\":true,\"1769\":true,\"1772\":true,\"1773\":true,\"1775\":true,\"1778\":true,\"1779\":true,\"1788\":true,\"1795\":true,\"1799\":true,\"1804\":true,\"1805\":true,\"1806\":true,\"1809\":true,\"1813\":true,\"1816\":true,\"1817\":true,\"1818\":true,\"1819\":true,\"1821\":true,\"1822\":true,\"1823\":true,\"1824\":true,\"1836\":true,\"1841\":true,\"1844\":true,\"1845\":true,\"1847\":true,\"1856\":true,\"1862\":true,\"1863\":true,\"1866\":true,\"1871\":true,\"1875\":true,\"1879\":true,\"1882\":true,\"1883\":true,\"1886\":true,\"1889\":true,\"1897\":true,\"1903\":true,\"1906\":true,\"1907\":true,\"1908\":true,\"1914\":true,\"1917\":true,\"1923\":true,\"1927\":true,\"1929\":true,\"1931\":true,\"1932\":true,\"1933\":true,\"1936\":true,\"1944\":true,\"1945\":true,\"1956\":true,\"1957\":true,\"1959\":true,\"1963\":true,\"1968\":true,\"1972\":true,\"1976\":true,\"1984\":true,\"1986\":true,\"1988\":true,\"1991\":true,\"1994\":true,\"1996\":true,\"2001\":true,\"2003\":true,\"2011\":true,\"2013\":true,\"2014\":true,\"2021\":true,\"2023\":true,\"2025\":true,\"2027\":true,\"2029\":true,\"2034\":true,\"2053\":true,\"2054\":true,\"2056\":true,\"2057\":true,\"2059\":true,\"2066\":true,\"2079\":true,\"2082\":true,\"2095\":true,\"2097\":true,\"2099\":true,\"2103\":true,\"2112\":true,\"2115\":true,\"2116\":true,\"2125\":true,\"2126\":true,\"2129\":true,\"2131\":true,\"2134\":true,\"2136\":true,\"2137\":true,\"2147\":true,\"2149\":true,\"2152\":true,\"2162\":true,\"2165\":true,\"2166\":true,\"2167\":true,\"2173\":true,\"2182\":true,\"2184\":true,\"2188\":true,\"2211\":true,\"2221\":true,\"2222\":true,\"2223\":true,\"2227\":true,\"2233\":true,\"2236\":true,\"2247\":true,\"2254\":true,\"2257\":true,\"2268\":true,\"2277\":true,\"2282\":true,\"2287\":true,\"2292\":true,\"2298\":true,\"2303\":true,\"2304\":true,\"2312\":true,\"2331\":true,\"2335\":true,\"2337\":true,\"2341\":true,\"2354\":true,\"2356\":true,\"2373\":true,\"2384\":true,\"2388\":true,\"2389\":true,\"2395\":true,\"2396\":true,\"2405\":true,\"2409\":true,\"2427\":true,\"2453\":true,\"2463\":true,\"2465\":true,\"2473\":true,\"2478\":true,\"2479\":true,\"2491\":true,\"2492\":true,\"2502\":true,\"2504\":true,\"2513\":true,\"2523\":true,\"2531\":true,\"2542\":true,\"2557\":true,\"2593\":true,\"2597\":true,\"2602\":true,\"2603\":true,\"2606\":true,\"2614\":true,\"2619\":true,\"2625\":true,\"2645\":true,\"2657\":true,\"2668\":true,\"2675\":true,\"2677\":true,\"2678\":true,\"2685\":true,\"2689\":true,\"2691\":true,\"2696\":true,\"2697\":true,\"2711\":true,\"2721\":true,\"2735\":true,\"2739\":true,\"2754\":true,\"2756\":true,\"2762\":true,\"2764\":true,\"2812\":true,\"2833\":true,\"2837\":true,\"2848\":true,\"2863\":true,\"2876\":true,\"2888\":true,\"2897\":true,\"2905\":true,\"2958\":true,\"2967\":true,\"2968\":true,\"2979\":true,\"2986\":true,\"2987\":true,\"2988\":true,\"3001\":true,\"3002\":true,\"3003\":true,\"3013\":true,\"3026\":true,\"3043\":true,\"3055\":true,\"3073\":true,\"3082\":true,\"3102\":true,\"3103\":true,\"3128\":true,\"3137\":true,\"3149\":true,\"3179\":true,\"3181\":true,\"3194\":true,\"3208\":true,\"3239\":true,\"3258\":true,\"3264\":true,\"3293\":true,\"3294\":true,\"3311\":true,\"3328\":true,\"3334\":true,\"3345\":true,\"3353\":true,\"3356\":true,\"3364\":true,\"3428\":true,\"3447\":true,\"3471\":true,\"3487\":true,\"3503\":true,\"3513\":true,\"3534\":true,\"3555\":true,\"3579\":true,\"3643\":true,\"3652\":true,\"3709\":true,\"3738\":true,\"3739\":true,\"3777\":true,\"3821\":true,\"3831\":true,\"3886\":true,\"4029\":true,\"4112\":true,\"4121\":true,\"4177\":true,\"4181\":true,\"4261\":true,\"4376\":true,\"4387\":true,\"4398\":true,\"4439\":true,\"4505\":true,\"4626\":true,\"4667\":true,\"4729\":true,\"4775\":true,\"4795\":true,\"4866\":true,\"5066\":true,\"5172\":true,\"5326\":true,\"5333\":true,\"5378\":true,\"5539\":true,\"5617\":true,\"5822\":true,\"5957\":true,\"5974\":true,\"6264\":true,\"6268\":true,\"6559\":true,\"7608\":true,\"7899\":true,\"8023\":true,\"8313\":true,\"\":true,\"039\":true,\"068\":true,\"0143\":true,\"0349\":true,\"013\":true,\"0269\":true,\"0309\":true,\"0107\":true,\"0215\":true,\"0106\":true,\"0226\":true,\"0067\":true,\"0201\":true,\"028\":true,\"0024\":true,\"0026\":true,\"0249\":true,\"0539\":true,\"0127\":true,\"0333\":true,\"0066\":true,\"0205\":true,\"0071\":true,\"0237\":true,\"0052\":true,\"016\":true,\"0059\":true,\"0178\":true,\"0013\":true,\"0147\":true,\"0025\":true,\"0162\":true,\"0095\":true,\"0294\":true,\"0585\":true,\"0158\":true,\"0364\":true,\"0048\":true,\"0187\":true,\"0033\":true,\"0199\":true,\"0047\":true,\"0155\":true,\"0069\":true,\"0189\":true,\"0086\":true,\"0221\":true,\"0112\":true,\"0072\":true,\"0049\":true,\"0479\":true,\"0149\":true,\"0355\":true,\"0244\":true,\"0135\":true,\"0301\":true,\"022\":true,\"011\":true,\"0229\":true,\"0088\":true,\"0223\":true,\"0094\":true,\"0043\":true,\"0079\":true,\"0105\":true,\"0255\":true,\"0036\":true,\"0076\":true,\"0264\":true,\"0125\":true,\"021\":true,\"0044\":true,\"0126\":true,\"0018\":true,\"0265\":true,\"0145\":true,\"0089\":true,\"0045\":true,\"008\":true,\"0057\":true,\"0356\":true,\"0318\":true,\"0608\":true,\"0151\":true,\"0357\":true,\"0211\":true,\"0142\":true,\"0308\":true,\"0115\":true,\"0102\":true,\"0099\":true,\"0233\":true,\"0002\":true,\"0289\":true,\"0011\":true,\"0195\":true,\"0055\":true,\"0083\":true,\"0065\":true,\"0231\":true,\"0073\":true,\"0181\":true,\"0042\":true,\"0078\":true,\"0213\":true,\"0196\":true,\"0157\":true,\"0131\":true,\"024\":true,\"0531\":true,\"0141\":true,\"0347\":true,\"0087\":true,\"0103\":true,\"0039\":true,\"0084\":true,\"0203\":true,\"0041\":true,\"0062\":true,\"005\":true,\"01\":true,\"0238\":true,\"0192\":true,\"009\":true,\"0198\":true,\"0051\":true,\"0186\":true,\"0153\":true,\"0324\":true,\"0614\":true,\"0368\":true,\"0068\":true,\"0234\":true,\"0185\":true,\"0108\":true,\"0242\":true,\"0278\":true,\"0391\":true,\"0075\":true,\"0214\":true,\"0144\":true,\"004\":true,\"0184\":true,\"0038\":true,\"0175\":true,\"0119\":true,\"0533\":true,\"0313\":true,\"0097\":true,\"0235\":true,\"0285\":true,\"0015\":true,\"0114\":true,\"0248\":true,\"0133\":true,\"027\":true,\"0312\":true,\"0603\":true,\"0113\":true,\"032\":true,\"0251\":true,\"0159\":true,\"0227\":true,\"0228\":true,\"0268\":true,\"029\":true,\"0581\":true,\"0129\":true,\"0116\":true,\"0282\":true,\"0093\":true,\"0063\":true,\"0009\":true,\"0281\":true,\"0021\":true,\"0014\":true,\"0137\":true,\"0029\":true,\"006\":true,\"0194\":true,\"0188\":true,\"0174\":true,\"0138\":true,\"05\":true,\"0123\":true,\"0329\":true,\"0121\":true,\"026\":true,\"0118\":true,\"0284\":true,\"0176\":true,\"0245\":true,\"0034\":true,\"0315\":true,\"0605\":true,\"0165\":true,\"0371\":true,\"0053\":true,\"0304\":true,\"0207\":true,\"0111\":true,\"023\":true,\"0197\":true,\"0348\":true,\"0639\":true,\"0168\":true,\"0374\":true,\"0225\":true,\"0299\":true,\"0037\":true,\"0503\":true,\"0337\":true,\"0296\":true,\"0117\":true,\"0224\":true,\"0212\":true,\"0061\":true,\"007\":true,\"0283\":true,\"0573\":true,\"0287\":true,\"0091\":true,\"018\":true,\"0218\":true,\"0012\":true,\"0058\":true,\"047\":true,\"0362\":true,\"0262\":true,\"0553\":true,\"0128\":true,\"0334\":true,\"0179\":true,\"0104\":true,\"0046\":true,\"0261\":true,\"0293\":true,\"0035\":true,\"0064\":true,\"0172\":true,\"001\":true,\"0032\":true,\"0136\":true,\"0624\":true,\"0148\":true,\"0354\":true,\"0167\":true,\"0222\":true,\"0096\":true,\"0279\":true,\"0487\":true,\"0271\":true,\"0152\":true,\"0007\":true,\"0163\":true,\"0426\":true,\"0217\":true,\"037\":true,\"0661\":true,\"0109\":true,\"0122\":true,\"0288\":true,\"0031\":true,\"0027\":true,\"0578\":true,\"0164\":true,\"0056\":true,\"0161\":true,\"0367\":true,\"0016\":true,\"0256\":true,\"0336\":true,\"0627\":true,\"0166\":true,\"0236\":true,\"019\":true,\"0442\":true,\"0139\":true,\"002\":true,\"0206\":true,\"003\":true,\"015\":true,\"0381\":true,\"0671\":true,\"0074\":true,\"0085\":true,\"0077\":true,\"0232\":true,\"0673\":true,\"0382\":true,\"0001\":true,\"0023\":true,\"0343\":true,\"062\":true,\"0295\":true,\"0101\":true,\"0302\":true,\"0593\":true,\"0325\":true,\"0254\":true,\"0276\":true,\"0376\":true,\"0667\":true,\"0252\":true,\"0202\":true,\"0098\":true,\"0209\":true,\"0321\":true,\"0612\":true,\"0146\":true,\"0352\":true,\"0267\":true,\"0082\":true,\"0241\":true,\"0386\":true,\"0677\":true,\"0132\":true,\"031\":true,\"0204\":true,\"0247\":true,\"0297\":true,\"06\":true,\"0373\":true,\"0344\":true,\"0634\":true,\"0345\":true,\"0527\":true,\"0322\":true,\"0019\":true,\"0208\":true,\"0239\":true,\"0005\":true,\"0358\":true,\"0335\":true,\"0523\":true,\"0191\":true,\"025\":true,\"0541\":true,\"0319\":true,\"0272\":true,\"052\":true,\"0253\":true,\"0006\":true,\"0154\":true,\"0323\":true,\"0353\":true,\"0169\":true,\"0366\":true,\"0657\":true,\"0363\":true,\"0257\":true,\"0081\":true,\"0879\":true,\"0588\":true,\"0028\":true,\"0311\":true,\"0124\":true,\"0326\":true,\"0407\":true,\"036\":true,\"0651\":true,\"0616\":true,\"0274\":true,\"0246\":true,\"0617\":true,\"0177\":true,\"0331\":true,\"0622\":true,\"0369\":true,\"0216\":true,\"0936\":true,\"0771\":true,\"0817\":true,\"0682\":true,\"061\":true,\"0473\":true,\"0564\":true,\"0961\":true,\"0821\":true,\"04\":true,\"0729\":true,\"0595\":true,\"0004\":true,\"0584\":true,\"0332\":true,\"0372\":true,\"0314\":true,\"0291\":true,\"0263\":true,\"0375\":true,\"0666\":true,\"0092\":true,\"0275\":true,\"0054\":true,\"014\":true,\"0306\":true,\"0193\":true,\"0547\":true,\"0572\":true,\"0134\":true,\"012\":true,\"0286\":true,\"0171\":true,\"0922\":true,\"0863\":true,\"0361\":true,\"0219\":true,\"0292\":true,\"0583\":true,\"0022\":true,\"0328\":true,\"0618\":true,\"0243\":true,\"0173\":true,\"0607\":true,\"0731\":true,\"0597\":true,\"0652\":true,\"0003\":true,\"0655\":true,\"0517\":true,\"0434\":true,\"0008\":true,\"0327\":true,\"0303\":true,\"0365\":true,\"0656\":true,\"0183\":true,\"0538\":true,\"0305\":true,\"0664\":true,\"0417\":true,\"0182\":true,\"0544\":true,\"035\":true,\"0644\":true,\"0351\":true,\"0638\":true,\"0482\":true,\"0659\":true,\"0359\":true,\"0277\":true,\"0592\":true,\"0419\":true,\"0776\":true,\"0398\":true,\"0259\":true,\"0316\":true,\"0476\":true,\"0425\":true,\"0513\":true,\"0266\":true,\"0451\":true,\"0571\":true,\"0396\":true,\"0568\":true,\"0957\":true,\"0726\":true,\"0788\":true,\"0649\":true,\"055\":true,\"0724\":true,\"0943\":true,\"0737\":true,\"0437\":true,\"0496\":true,\"0017\":true,\"0338\":true,\"0629\":true,\"03\":true,\"0393\":true,\"0384\":true,\"0378\":true,\"0448\":true,\"0449\":true,\"0383\":true,\"0565\":true,\"0641\":true,\"0317\":true,\"0307\":true,\"0648\":true,\"0416\":true,\"0868\":true,\"048\":true,\"0258\":true,\"034\":true,\"0631\":true,\"0395\":true,\"0686\":true,\"0681\":true,\"0534\":true,\"0341\":true,\"0515\":true,\"0156\":true,\"0934\":true,\"0461\":true,\"0942\":true,\"0823\":true,\"0715\":true,\"0647\":true,\"0683\":true,\"0409\":true,\"0412\":true,\"0628\":true,\"0609\":true,\"0389\":true,\"0968\":true,\"0399\":true,\"0403\":true,\"0546\":true,\"0589\":true,\"0574\":true,\"096\":true,\"0273\":true,\"0418\":true,\"086\":true,\"0464\":true,\"0722\":true,\"0878\":true,\"054\":true,\"0625\":true,\"0665\":true,\"0387\":true,\"0678\":true,\"0346\":true,\"0632\":true,\"0663\":true,\"017\":true,\"0963\":true,\"0837\":true,\"0467\":true,\"045\":true,\"0709\":true,\"0543\":true,\"0971\":true,\"073\":true,\"056\":true,\"0298\":true,\"0901\":true,\"043\":true,\"0586\":true,\"0499\":true,\"0536\":true,\"0537\":true,\"057\":true,\"094\":true,\"0745\":true,\"0738\":true,\"0524\":true,\"0739\":true,\"041\":true,\"0497\":true,\"065\":true,\"0606\":true,\"091\":true,\"0619\":true,\"0854\":true,\"0711\":true,\"0576\":true,\"0444\":true,\"0626\":true,\"02\":true,\"038\":true,\"0519\":true,\"0654\":true,\"0436\":true,\"0727\":true,\"0979\":true,\"0689\":true,\"0814\":true,\"0492\":true,\"0566\":true,\"0645\":true,\"049\":true,\"0495\":true,\"053\":true,\"0567\":true,\"0459\":true,\"0561\":true,\"0514\":true,\"0377\":true,\"0716\":true,\"0812\":true,\"0646\":true,\"0917\":true,\"0809\":true,\"0826\":true,\"0557\":true,\"0839\":true,\"0548\":true,\"0643\":true,\"0339\":true,\"0489\":true,\"0636\":true,\"063\":true,\"0474\":true,\"0342\":true,\"0883\":true,\"0414\":true,\"088\":true,\"0743\":true,\"0937\":true,\"0674\":true,\"0701\":true,\"044\":true,\"033\":true,\"0621\":true,\"0594\":true,\"0876\":true,\"0504\":true,\"0501\":true,\"0529\":true,\"0528\":true,\"0613\":true,\"0542\":true,\"059\":true,\"0599\":true,\"0432\":true,\"0466\":true,\"0598\":true,\"0623\":true,\"0428\":true,\"0458\":true,\"0493\":true,\"0411\":true,\"0978\":true,\"0772\":true,\"0447\":true,\"0637\":true,\"0786\":true,\"0717\":true,\"0424\":true,\"0735\":true,\"0707\":true,\"0397\":true,\"0415\":true,\"0429\":true,\"0604\":true,\"0798\":true,\"0679\":true,\"0675\":true,\"0921\":true,\"0512\":true,\"0662\":true,\"0562\":true,\"0851\":true,\"0687\":true,\"0441\":true,\"042\":true,\"0484\":true,\"0438\":true,\"0712\":true,\"0402\":true,\"0886\":true,\"0525\":true,\"064\":true,\"0749\":true,\"0965\":true,\"0799\":true,\"0765\":true,\"09\":true,\"0861\":true,\"0508\":true,\"0653\":true,\"0535\":true,\"0427\":true,\"0394\":true,\"0685\":true,\"0939\":true,\"0866\":true,\"066\":true,\"0413\":true,\"051\":true,\"0462\":true,\"0668\":true,\"0973\":true,\"0794\":true,\"0744\":true,\"0472\":true,\"0741\":true,\"0454\":true,\"0502\":true,\"0801\":true,\"0938\":true,\"0732\":true,\"0787\":true,\"0469\":true,\"0915\":true,\"087\":true,\"0713\":true,\"0435\":true,\"0575\":true,\"0579\":true,\"058\":true,\"0577\":true,\"0601\":true,\"0551\":true,\"0908\":true,\"0457\":true,\"0486\":true,\"0471\":true,\"0379\":true,\"0696\":true,\"0545\":true,\"0532\":true,\"0819\":true,\"0446\":true,\"0587\":true,\"0658\":true,\"0558\":true,\"0555\":true,\"0526\":true,\"0388\":true,\"0408\":true,\"0699\":true,\"0611\":true,\"0521\":true,\"0552\":true,\"0516\":true,\"0764\":true,\"074\":true,\"0475\":true,\"0392\":true,\"0509\":true,\"0554\":true,\"0406\":true,\"0807\":true,\"0805\":true,\"0691\":true,\"0505\":true,\"0918\":true,\"0556\":true,\"0453\":true,\"0975\":true,\"0769\":true,\"0808\":true,\"0596\":true,\"093\":true,\"0844\":true,\"0563\":true,\"0955\":true,\"082\":true,\"0987\":true,\"085\":true,\"0736\":true,\"0992\":true,\"0697\":true,\"0852\":true,\"0828\":true,\"0888\":true,\"0465\":true,\"0456\":true,\"0507\":true,\"0887\":true,\"0455\":true,\"0385\":true,\"0877\":true,\"0845\":true,\"0708\":true,\"0999\":true,\"0793\":true,\"0904\":true,\"0833\":true,\"0725\":true,\"0994\":true,\"0931\":true,\"0669\":true,\"0813\":true,\"0477\":true,\"0549\":true,\"0602\":true,\"0949\":true,\"0811\":true,\"0792\":true,\"0615\":true,\"0784\":true,\"0494\":true,\"067\":true,\"0498\":true,\"0954\":true,\"0815\":true,\"0905\":true,\"0848\":true,\"0443\":true,\"0491\":true,\"0591\":true,\"0694\":true,\"0829\":true,\"0945\":true,\"0761\":true,\"0859\":true,\"0882\":true,\"0676\":true,\"0488\":true,\"0752\":true,\"0899\":true,\"0693\":true,\"0705\":true,\"0559\":true,\"0439\":true,\"0789\":true,\"0747\":true,\"0405\":true,\"0695\":true,\"0721\":true,\"0431\":true,\"0485\":true,\"0785\":true,\"0759\":true,\"0522\":true,\"0714\":true,\"0843\":true,\"0902\":true,\"0768\":true,\"0468\":true,\"0775\":true,\"0478\":true,\"0818\":true,\"071\":true,\"0869\":true,\"0842\":true,\"0723\":true,\"0422\":true,\"0757\":true,\"0569\":true,\"0858\":true,\"0633\":true,\"0463\":true,\"0635\":true,\"0642\":true,\"0481\":true,\"097\":true,\"0831\":true,\"0698\":true,\"0672\":true,\"0421\":true,\"0907\":true,\"0873\":true,\"095\":true,\"0692\":true,\"069\":true,\"0506\":true,\"0972\":true,\"046\":true,\"0911\":true,\"0932\":true,\"0834\":true,\"0914\":true,\"0985\":true,\"0865\":true,\"0445\":true,\"0684\":true,\"084\":true,\"0969\":true,\"0925\":true,\"0806\":true,\"0688\":true,\"078\":true,\"079\":true,\"081\":true,\"083\":true,\"0803\":true,\"0795\":true,\"0964\":true,\"0758\":true,\"0767\":true,\"0728\":true,\"0976\":true,\"0923\":true,\"0582\":true,\"0913\":true,\"07\":true,\"0881\":true,\"0804\":true,\"0452\":true,\"08\":true,\"0733\":true,\"0892\":true,\"0856\":true,\"0748\":true,\"0953\":true,\"0967\":true,\"0909\":true,\"0849\":true,\"0702\":true,\"0893\":true,\"0983\":true,\"0853\":true,\"0991\":true,\"0941\":true,\"0947\":true,\"0518\":true,\"0401\":true,\"0511\":true,\"0864\":true,\"0734\":true,\"0836\":true,\"0423\":true,\"0962\":true,\"0824\":true,\"0802\":true,\"0857\":true,\"072\":true,\"0997\":true,\"0755\":true,\"0959\":true,\"0703\":true,\"0816\":true,\"0404\":true,\"0871\":true,\"0706\":true,\"0756\":true,\"0718\":true,\"0774\":true,\"0483\":true,\"0929\":true,\"0966\":true,\"077\":true,\"0956\":true,\"0835\":true,\"0846\":true,\"0791\":true,\"0982\":true,\"0884\":true,\"0841\":true,\"0704\":true,\"0919\":true,\"0872\":true,\"0862\":true,\"0889\":true,\"0924\":true,\"0773\":true,\"0754\":true,\"0958\":true,\"0827\":true,\"0906\":true,\"0998\":true,\"0719\":true,\"0783\":true,\"0996\":true,\"0433\":true,\"0832\":true,\"0951\":true,\"0781\":true,\"0928\":true,\"0885\":true,\"0896\":true,\"0993\":true,\"0898\":true,\"0916\":true,\"0779\":true,\"0903\":true,\"0981\":true,\"0935\":true,\"0777\":true,\"0742\":true,\"0796\":true,\"0995\":true,\"0988\":true,\"0946\":true,\"0825\":true,\"098\":true,\"075\":true,\"0746\":true,\"0797\":true,\"0766\":true,\"0822\":true,\"0926\":true,\"0867\":true,\"0763\":true,\"0897\":true,\"076\":true,\"0974\":true,\"0782\":true},\"vocabularySize\":1745,\"wordCount\":{\"0\":35261,\"1\":18782,\"2\":18694,\"3\":13936,\"4\":16006},\"wordFrequencyCount\":{\"0\":{\"0\":17154,\"\":953,\"039\":7,\"068\":8,\"0143\":58,\"0349\":28,\"013\":62,\"0269\":37,\"0309\":29,\"0107\":112,\"0215\":61,\"0106\":106,\"0226\":50,\"0067\":60,\"0201\":51,\"028\":28,\"0024\":34,\"0026\":45,\"0318\":10,\"0608\":9,\"0151\":31,\"0357\":41,\"0072\":53,\"0211\":53,\"0142\":39,\"0308\":40,\"0115\":100,\"0223\":69,\"0102\":101,\"0221\":76,\"0099\":99,\"0233\":51,\"0052\":63,\"0189\":38,\"0047\":55,\"0049\":55,\"029\":22,\"0581\":6,\"0158\":33,\"0364\":35,\"0129\":37,\"0268\":38,\"0116\":110,\"0282\":24,\"0093\":88,\"0095\":73,\"0214\":56,\"0063\":45,\"0198\":38,\"0084\":73,\"0348\":21,\"0639\":9,\"0168\":41,\"0374\":39,\"0086\":79,\"0225\":75,\"0133\":70,\"0299\":29,\"021\":58,\"0213\":60,\"0103\":95,\"0237\":68,\"0075\":58,\"004\":60,\"0037\":59,\"037\":23,\"0661\":4,\"0109\":105,\"0248\":58,\"0122\":85,\"0288\":24,\"0088\":73,\"0195\":43,\"0118\":76,\"0089\":85,\"027\":43,\"0031\":61,\"0027\":55,\"0381\":5,\"0671\":4,\"0117\":106,\"0324\":14,\"0074\":44,\"0085\":61,\"0251\":65,\"0077\":54,\"0184\":29,\"0064\":44,\"0197\":37,\"0232\":48,\"0059\":48,\"0013\":5,\"0329\":12,\"062\":10,\"0238\":73,\"0295\":13,\"0224\":68,\"0242\":65,\"0101\":109,\"0235\":71,\"007\":40,\"0207\":51,\"0038\":62,\"0044\":57,\"0302\":27,\"0593\":3,\"0119\":68,\"0325\":20,\"0254\":37,\"011\":98,\"0276\":24,\"005\":64,\"0218\":84,\"0042\":63,\"0179\":24,\"0061\":42,\"0376\":7,\"0667\":7,\"0167\":34,\"0113\":109,\"0252\":46,\"0123\":72,\"0289\":24,\"0202\":51,\"0098\":78,\"0209\":66,\"0034\":55,\"0025\":43,\"0321\":12,\"0612\":7,\"0146\":44,\"0352\":25,\"0267\":41,\"0082\":67,\"019\":30,\"0114\":95,\"022\":73,\"0104\":107,\"0241\":66,\"0043\":68,\"0386\":7,\"0677\":7,\"016\":31,\"0367\":29,\"0132\":57,\"0271\":38,\"0144\":53,\"031\":27,\"0096\":78,\"0204\":41,\"0083\":75,\"0217\":68,\"0108\":99,\"0245\":70,\"06\":6,\"0373\":28,\"0127\":64,\"0265\":33,\"008\":54,\"0188\":37,\"0236\":63,\"0078\":55,\"0055\":48,\"0192\":46,\"0344\":23,\"0634\":7,\"0139\":58,\"0345\":29,\"024\":65,\"0056\":49,\"0164\":30,\"009\":65,\"0053\":48,\"0035\":57,\"0527\":2,\"0322\":18,\"0019\":9,\"0185\":24,\"0105\":93,\"0073\":57,\"0208\":74,\"0239\":75,\"0066\":42,\"025\":50,\"0541\":2,\"0319\":16,\"0272\":45,\"0097\":90,\"0009\":5,\"0128\":57,\"0069\":54,\"0323\":19,\"0614\":8,\"0147\":33,\"0353\":29,\"0065\":42,\"0283\":25,\"0169\":16,\"0222\":66,\"0366\":28,\"0657\":8,\"0157\":33,\"0363\":29,\"0257\":29,\"0081\":59,\"0126\":59,\"0032\":70,\"036\":33,\"0651\":8,\"0111\":113,\"0249\":44,\"0212\":62,\"0205\":58,\"003\":53,\"0326\":11,\"0617\":8,\"0165\":33,\"0371\":30,\"0228\":58,\"0177\":20,\"0196\":32,\"0057\":58,\"0331\":18,\"0622\":12,\"0163\":28,\"0369\":30,\"0094\":79,\"0216\":58,\"0045\":64,\"0039\":64,\"0375\":11,\"0666\":4,\"0092\":78,\"0231\":64,\"023\":64,\"0087\":64,\"0138\":40,\"0275\":32,\"0281\":35,\"0572\":5,\"0134\":44,\"012\":68,\"0286\":20,\"0091\":75,\"0036\":71,\"0171\":18,\"0174\":17,\"0062\":55,\"0058\":47,\"0155\":34,\"0361\":31,\"0076\":54,\"0247\":54,\"0112\":88,\"0219\":68,\"0172\":11,\"0041\":54,\"0655\":8,\"0314\":12,\"0124\":59,\"0262\":31,\"0191\":29,\"0029\":47,\"0327\":17,\"0618\":12,\"0028\":44,\"0365\":29,\"0656\":13,\"0183\":28,\"0664\":7,\"015\":21,\"0131\":63,\"0287\":19,\"0199\":43,\"0644\":14,\"0145\":53,\"0351\":35,\"0312\":40,\"0659\":6,\"0153\":42,\"0359\":38,\"0136\":54,\"014\":49,\"0277\":23,\"0023\":41,\"0301\":28,\"0592\":5,\"0336\":23,\"0054\":57,\"0616\":12,\"0293\":28,\"0193\":27,\"0152\":25,\"0358\":30,\"0246\":50,\"0046\":60,\"0154\":25,\"0068\":32,\"0338\":19,\"0629\":6,\"0149\":23,\"0355\":32,\"035\":25,\"0641\":7,\"0317\":10,\"01\":87,\"0141\":32,\"0307\":24,\"0648\":12,\"0356\":25,\"018\":17,\"0395\":2,\"0686\":3,\"0264\":45,\"0391\":6,\"0681\":8,\"0296\":28,\"0022\":31,\"0603\":9,\"0135\":39,\"0341\":22,\"0393\":4,\"0683\":4,\"0125\":67,\"0021\":17,\"0628\":16,\"0334\":19,\"0266\":34,\"0051\":51,\"0335\":12,\"0625\":13,\"0306\":32,\"0665\":15,\"0229\":54,\"0387\":8,\"0678\":7,\"0346\":28,\"0632\":7,\"0253\":42,\"0227\":64,\"0372\":25,\"0663\":9,\"0261\":38,\"017\":15,\"0347\":16,\"0638\":13,\"0048\":62,\"0298\":22,\"0383\":4,\"0673\":6,\"0137\":44,\"065\":8,\"0162\":27,\"0368\":26,\"0033\":70,\"0315\":11,\"0606\":11,\"0187\":31,\"0273\":33,\"0626\":12,\"0256\":41,\"02\":47,\"0654\":8,\"0332\":23,\"0186\":27,\"0436\":1,\"0727\":1,\"001\":3,\"0643\":11,\"034\":14,\"0305\":38,\"0243\":77,\"0194\":32,\"0203\":46,\"0079\":60,\"0339\":22,\"063\":7,\"0234\":67,\"0316\":10,\"0607\":5,\"0342\":20,\"0258\":26,\"0333\":21,\"0121\":66,\"0674\":3,\"041\":2,\"0701\":1,\"0304\":29,\"0263\":39,\"0017\":6,\"0016\":6,\"033\":21,\"0621\":11,\"026\":41,\"0173\":21,\"006\":52,\"0624\":9,\"0176\":16,\"0294\":27,\"0584\":6,\"0337\":27,\"0181\":26,\"0613\":15,\"0291\":25,\"0292\":19,\"0583\":7,\"0159\":28,\"0599\":8,\"0311\":33,\"0161\":29,\"0284\":21,\"0382\":6,\"0313\":19,\"0598\":7,\"03\":21,\"0244\":54,\"038\":3,\"0647\":11,\"0623\":12,\"0178\":13,\"0297\":29,\"0547\":3,\"0604\":3,\"0585\":8,\"0646\":12,\"0148\":26,\"0354\":39,\"0662\":13,\"0343\":18,\"0493\":1,\"0303\":27,\"0529\":2,\"0206\":45,\"0362\":30,\"0652\":5,\"0588\":6,\"0285\":19,\"0166\":27,\"0636\":12,\"0274\":23,\"0384\":3,\"0675\":2,\"0653\":8,\"0609\":4,\"0394\":3,\"0685\":2,\"0605\":7,\"0071\":47,\"0377\":8,\"0668\":13,\"0328\":24,\"0619\":9,\"0255\":32,\"066\":8,\"0575\":5,\"0645\":14,\"0601\":6,\"0551\":3,\"0658\":6,\"0408\":3,\"0699\":3,\"0578\":4,\"064\":11,\"0259\":34,\"002\":15,\"0567\":6,\"0557\":4,\"0571\":4,\"0378\":17,\"0548\":2,\"0018\":13,\"0535\":1,\"032\":11,\"0596\":6,\"0669\":13,\"0568\":3,\"0182\":16,\"0602\":6,\"0532\":1,\"0279\":19,\"0615\":7,\"0611\":8,\"0525\":4,\"0591\":5,\"0175\":11,\"061\":8,\"057\":4,\"0403\":1,\"0694\":1,\"0008\":1,\"0156\":29,\"0631\":8,\"0278\":16,\"0635\":9,\"0392\":2,\"0642\":10,\"0579\":2,\"0561\":1,\"0389\":9,\"0679\":4,\"0649\":9,\"0554\":4,\"0496\":1,\"0633\":5,\"0556\":2,\"0558\":2,\"0003\":1,\"0627\":7,\"0546\":3,\"0684\":3,\"0553\":2,\"0006\":2,\"0566\":4,\"0637\":4,\"0555\":1,\"0406\":1,\"0697\":1,\"0379\":5,\"067\":4,\"0544\":2,\"0577\":2,\"0001\":1,\"0552\":1,\"0672\":5,\"058\":2,\"0569\":2,\"0573\":6,\"0545\":4,\"0399\":1,\"0689\":1,\"0587\":3,\"0589\":2,\"059\":6,\"0388\":2,\"0595\":4,\"0676\":4,\"0597\":6,\"0534\":2,\"0562\":3,\"054\":1,\"0521\":1,\"0682\":3,\"056\":1,\"0412\":1,\"0703\":1,\"0586\":1,\"0396\":2,\"0528\":1,\"0564\":2,\"0404\":2,\"0695\":2,\"0401\":2,\"0692\":2,\"0411\":1,\"0702\":1,\"0014\":4,\"0594\":1,\"052\":1,\"0004\":1,\"0559\":2,\"0398\":2,\"0688\":3,\"07\":1,\"0574\":1,\"0385\":1,\"0565\":2,\"0405\":1,\"0696\":1,\"0397\":1,\"0576\":2,\"0549\":2,\"0011\":1,\"0466\":1,\"0582\":3,\"051\":1,\"0542\":1,\"0002\":2,\"0516\":1,\"0539\":3,\"055\":1,\"0415\":1,\"0706\":1,\"0015\":2,\"0486\":1,\"0536\":1,\"0498\":1,\"0513\":1,\"04\":1,\"0691\":1,\"0488\":1},\"1\":{\"0\":9234,\"1\":1,\"101\":1,\"102\":2,\"105\":2,\"107\":3,\"108\":1,\"109\":1,\"113\":1,\"114\":2,\"116\":1,\"117\":1,\"118\":1,\"119\":1,\"123\":1,\"124\":1,\"125\":2,\"128\":1,\"131\":1,\"132\":1,\"135\":1,\"136\":1,\"145\":1,\"151\":1,\"156\":1,\"159\":1,\"172\":1,\"183\":1,\"185\":1,\"189\":1,\"199\":1,\"207\":1,\"211\":1,\"236\":1,\"242\":1,\"258\":1,\"335\":1,\"364\":1,\"1001\":2,\"1003\":2,\"1005\":1,\"1008\":1,\"1009\":2,\"1013\":1,\"1018\":3,\"1019\":1,\"1025\":4,\"1026\":3,\"1027\":1,\"1031\":1,\"1033\":2,\"1034\":1,\"1038\":1,\"1044\":1,\"1047\":2,\"1048\":1,\"1049\":1,\"1054\":1,\"1055\":1,\"1057\":2,\"1059\":1,\"1062\":1,\"1063\":1,\"1066\":1,\"1078\":1,\"1079\":1,\"1085\":1,\"1088\":1,\"1091\":2,\"1092\":1,\"1094\":1,\"1095\":1,\"1096\":1,\"1097\":2,\"1098\":1,\"1099\":1,\"1103\":1,\"1104\":2,\"1105\":1,\"1111\":1,\"1114\":1,\"1117\":1,\"1121\":1,\"1123\":2,\"1124\":1,\"1125\":1,\"1126\":1,\"1127\":1,\"1128\":1,\"1129\":1,\"1139\":1,\"1141\":1,\"1142\":1,\"1143\":2,\"1147\":1,\"1149\":1,\"1151\":1,\"1152\":1,\"1156\":1,\"1158\":2,\"1163\":1,\"1164\":1,\"1171\":1,\"1173\":1,\"1174\":1,\"1176\":1,\"1177\":2,\"1179\":1,\"1181\":1,\"1186\":1,\"1187\":2,\"1192\":1,\"1194\":1,\"1198\":1,\"1199\":2,\"1202\":2,\"1208\":1,\"1211\":1,\"1212\":1,\"1214\":1,\"1217\":2,\"1219\":3,\"1221\":1,\"1223\":1,\"1224\":1,\"1225\":1,\"1231\":1,\"1232\":1,\"1233\":1,\"1242\":1,\"1249\":1,\"1251\":2,\"1258\":1,\"1259\":1,\"1261\":1,\"1263\":1,\"1265\":2,\"1266\":3,\"1269\":1,\"1278\":1,\"1279\":1,\"1281\":1,\"1287\":1,\"1291\":3,\"1297\":2,\"1318\":1,\"1322\":1,\"1348\":1,\"1349\":1,\"1351\":1,\"1353\":1,\"1354\":1,\"1367\":1,\"1369\":1,\"1373\":1,\"1375\":1,\"1384\":1,\"1388\":2,\"1393\":1,\"1395\":3,\"1398\":1,\"1401\":1,\"1405\":1,\"1415\":1,\"1418\":1,\"1425\":1,\"1429\":1,\"1431\":1,\"1448\":1,\"1449\":1,\"1454\":1,\"1456\":1,\"1468\":1,\"1471\":1,\"1472\":1,\"1478\":2,\"1479\":1,\"1481\":1,\"1504\":2,\"1514\":1,\"1515\":2,\"1518\":1,\"1519\":1,\"1521\":1,\"1526\":1,\"1527\":2,\"1536\":1,\"1539\":2,\"1549\":1,\"1551\":1,\"1556\":1,\"1569\":1,\"1581\":1,\"1583\":1,\"1616\":1,\"1618\":1,\"1638\":1,\"1643\":1,\"1646\":1,\"1648\":1,\"1657\":1,\"1666\":1,\"1674\":1,\"1684\":1,\"1685\":1,\"1691\":1,\"1694\":1,\"1699\":1,\"1721\":1,\"1733\":1,\"1744\":1,\"1762\":1,\"1769\":1,\"1775\":1,\"1779\":1,\"1795\":1,\"1806\":1,\"1809\":2,\"1813\":1,\"1817\":1,\"1818\":1,\"1819\":1,\"1824\":1,\"1841\":1,\"1844\":1,\"1847\":1,\"1856\":1,\"1862\":1,\"1889\":1,\"1914\":1,\"1927\":1,\"1956\":1,\"1968\":1,\"1991\":1,\"1996\":1,\"2014\":1,\"2034\":1,\"2056\":1,\"2082\":1,\"2095\":1,\"2097\":1,\"2125\":1,\"2129\":1,\"2134\":1,\"2147\":1,\"2152\":1,\"2165\":1,\"2188\":1,\"2222\":1,\"2282\":1,\"2287\":1,\"2331\":1,\"2373\":2,\"2388\":1,\"2463\":1,\"2479\":1,\"2542\":1,\"2606\":1,\"2619\":1,\"2696\":1,\"2697\":1,\"2735\":1,\"2754\":1,\"2812\":1,\"2833\":1,\"2837\":1,\"2897\":1,\"2986\":1,\"2988\":1,\"3002\":1,\"3003\":1,\"3026\":1,\"3043\":1,\"3073\":1,\"3102\":1,\"3128\":1,\"3208\":1,\"3294\":1,\"3334\":1,\"3364\":1,\"3487\":1,\"3513\":1,\"3652\":1,\"3777\":1,\"4775\":1,\"5066\":1,\"5333\":1,\"5539\":1,\"5974\":1,\"6264\":1,\"8023\":1,\"8313\":1,\"\":319,\"0189\":17,\"0479\":2,\"0149\":19,\"0355\":6,\"0106\":32,\"0244\":34,\"0135\":27,\"0301\":11,\"0112\":41,\"022\":22,\"011\":41,\"0229\":26,\"0088\":39,\"0223\":24,\"0094\":43,\"0043\":28,\"0079\":31,\"0105\":43,\"0255\":12,\"0036\":31,\"013\":22,\"0076\":30,\"0264\":21,\"0125\":24,\"021\":28,\"0044\":36,\"0126\":30,\"0018\":24,\"0265\":13,\"0145\":22,\"0089\":39,\"0045\":33,\"008\":40,\"0057\":34,\"0356\":9,\"0155\":19,\"024\":24,\"0531\":4,\"0141\":27,\"0347\":4,\"0087\":39,\"0226\":22,\"0103\":41,\"0269\":16,\"0039\":30,\"0147\":14,\"0084\":36,\"0203\":19,\"0086\":35,\"0221\":25,\"0041\":24,\"0178\":21,\"0062\":34,\"0312\":12,\"0603\":4,\"0113\":33,\"032\":4,\"0251\":17,\"0278\":11,\"0051\":35,\"0159\":23,\"0108\":41,\"0227\":23,\"0228\":22,\"0131\":25,\"0268\":16,\"0049\":27,\"0009\":23,\"0281\":16,\"0021\":20,\"0186\":22,\"0014\":26,\"0153\":19,\"0137\":32,\"0029\":27,\"004\":30,\"0068\":35,\"0233\":23,\"006\":33,\"0194\":22,\"0188\":20,\"0174\":15,\"0138\":39,\"0262\":22,\"0553\":6,\"0128\":35,\"0334\":7,\"0063\":41,\"0201\":25,\"0117\":42,\"0282\":13,\"0071\":38,\"0179\":19,\"0104\":34,\"0224\":32,\"0046\":36,\"0181\":21,\"0069\":42,\"0055\":45,\"0151\":25,\"0442\":5,\"0075\":36,\"0139\":21,\"002\":14,\"0099\":34,\"0206\":23,\"003\":22,\"015\":23,\"009\":39,\"0225\":30,\"0212\":24,\"0673\":1,\"0382\":3,\"0185\":20,\"0001\":24,\"0165\":22,\"0064\":28,\"0026\":29,\"0161\":21,\"0023\":32,\"0114\":34,\"0343\":11,\"0523\":5,\"0337\":6,\"0056\":36,\"0195\":23,\"0025\":31,\"0191\":30,\"0019\":14,\"0127\":24,\"018\":17,\"007\":53,\"0204\":26,\"0034\":29,\"0879\":1,\"0588\":2,\"031\":8,\"0083\":52,\"0028\":21,\"0311\":11,\"0122\":34,\"0012\":24,\"0124\":36,\"0326\":4,\"0407\":3,\"0292\":10,\"0583\":3,\"0236\":21,\"0022\":19,\"016\":14,\"0053\":39,\"0219\":19,\"0115\":35,\"0242\":23,\"0073\":33,\"0208\":25,\"0216\":27,\"0058\":36,\"0328\":7,\"0618\":3,\"0358\":11,\"0085\":40,\"0047\":29,\"0213\":24,\"0048\":38,\"0123\":25,\"0243\":20,\"0173\":18,\"0067\":38,\"0002\":22,\"0192\":14,\"0015\":22,\"0091\":55,\"0198\":21,\"0607\":2,\"0487\":3,\"0731\":1,\"0597\":2,\"0066\":32,\"0581\":2,\"0652\":1,\"0517\":3,\"0154\":23,\"0052\":38,\"014\":22,\"0166\":24,\"0059\":25,\"0434\":5,\"0314\":6,\"0335\":8,\"0291\":7,\"0095\":36,\"0205\":21,\"01\":35,\"0008\":19,\"0107\":42,\"0197\":22,\"0313\":8,\"0373\":10,\"0167\":25,\"0065\":33,\"0007\":21,\"0092\":42,\"0093\":38,\"0248\":24,\"0538\":3,\"0305\":7,\"0254\":19,\"0184\":17,\"0164\":23,\"0776\":2,\"0272\":15,\"0398\":5,\"0259\":14,\"0082\":38,\"0042\":24,\"0316\":8,\"0098\":38,\"0476\":2,\"0425\":6,\"0245\":20,\"0246\":16,\"0158\":12,\"0077\":37,\"0031\":27,\"0074\":33,\"0318\":4,\"0279\":16,\"0175\":18,\"0011\":26,\"028\":12,\"0078\":44,\"0284\":5,\"0202\":27,\"0061\":43,\"0017\":15,\"0218\":16,\"0142\":22,\"0133\":28,\"0321\":6,\"0416\":5,\"0868\":1,\"048\":3,\"0005\":18,\"0211\":19,\"0249\":22,\"0172\":16,\"0121\":28,\"0258\":19,\"0609\":3,\"0109\":40,\"0389\":3,\"0271\":15,\"0968\":1,\"0677\":2,\"0152\":25,\"0353\":9,\"0038\":26,\"0096\":34,\"0399\":2,\"0403\":8,\"012\":35,\"0252\":20,\"0241\":23,\"0116\":36,\"0235\":21,\"0143\":19,\"0193\":21,\"0605\":6,\"005\":26,\"0101\":34,\"0267\":19,\"0182\":16,\"0033\":23,\"0901\":2,\"061\":2,\"0006\":23,\"0054\":28,\"055\":1,\"043\":6,\"0144\":28,\"0374\":7,\"0418\":4,\"0536\":2,\"0361\":7,\"0134\":29,\"03\":7,\"026\":15,\"0097\":35,\"0199\":21,\"0035\":24,\"0102\":42,\"0519\":4,\"0365\":7,\"0111\":47,\"0287\":9,\"0016\":20,\"0307\":8,\"0081\":33,\"02\":21,\"039\":5,\"0176\":22,\"0645\":4,\"0354\":5,\"049\":3,\"0283\":14,\"0634\":2,\"0495\":2,\"053\":4,\"0364\":7,\"0567\":7,\"0459\":5,\"0561\":3,\"0366\":4,\"0231\":26,\"0514\":1,\"0377\":3,\"0716\":1,\"0883\":3,\"0414\":2,\"088\":1,\"0743\":5,\"0937\":1,\"0572\":6,\"0129\":26,\"0295\":8,\"0136\":30,\"0032\":19,\"0217\":23,\"0214\":15,\"0504\":4,\"0013\":28,\"0183\":25,\"045\":1,\"0432\":4,\"0293\":7,\"0304\":7,\"0037\":25,\"0428\":2,\"0458\":1,\"017\":18,\"0156\":21,\"0978\":1,\"0772\":1,\"0447\":6,\"0308\":12,\"0637\":3,\"0786\":5,\"0666\":2,\"0717\":1,\"0424\":7,\"0661\":2,\"0232\":25,\"0963\":2,\"0798\":1,\"0351\":5,\"0119\":32,\"0256\":15,\"0679\":3,\"0675\":1,\"0274\":20,\"0564\":2,\"0024\":20,\"0369\":5,\"0162\":28,\"0438\":3,\"0299\":7,\"0368\":12,\"0319\":5,\"0146\":20,\"0712\":1,\"0648\":4,\"0215\":13,\"0402\":1,\"0608\":2,\"0247\":18,\"09\":1,\"0861\":1,\"0655\":1,\"0508\":1,\"0493\":6,\"0327\":6,\"0004\":16,\"0566\":3,\"052\":4,\"0263\":18,\"0234\":17,\"0294\":9,\"0345\":10,\"0589\":4,\"0359\":7,\"0132\":34,\"0372\":7,\"0502\":5,\"0257\":19,\"0482\":7,\"0072\":33,\"0222\":14,\"0003\":20,\"0585\":3,\"0357\":9,\"0169\":24,\"041\":7,\"0336\":8,\"0118\":23,\"0253\":14,\"0787\":2,\"0496\":3,\"0412\":3,\"0332\":5,\"0626\":4,\"0273\":11,\"0286\":8,\"0577\":3,\"0338\":6,\"027\":16,\"0449\":7,\"0362\":7,\"019\":15,\"0238\":19,\"0446\":3,\"0298\":10,\"0574\":1,\"0429\":4,\"037\":8,\"0277\":12,\"0568\":5,\"0157\":19,\"0239\":27,\"038\":4,\"036\":6,\"0309\":1,\"0027\":19,\"0168\":24,\"0266\":16,\"0509\":2,\"0288\":8,\"0289\":8,\"0207\":16,\"0196\":16,\"0322\":7,\"0344\":8,\"0163\":24,\"025\":13,\"0461\":4,\"0171\":13,\"0562\":4,\"0148\":11,\"0544\":1,\"0323\":2,\"0383\":3,\"0617\":2,\"0342\":8,\"0918\":2,\"0501\":5,\"0451\":2,\"029\":6,\"058\":4,\"0325\":7,\"0187\":13,\"0512\":3,\"0736\":1,\"0529\":3,\"0992\":1,\"0367\":9,\"0697\":2,\"0852\":3,\"0306\":8,\"0392\":4,\"0999\":1,\"0793\":1,\"096\":2,\"0904\":1,\"0833\":2,\"0725\":2,\"0994\":2,\"0931\":2,\"0794\":2,\"085\":2,\"0813\":2,\"0543\":3,\"0436\":4,\"0631\":1,\"0456\":4,\"0371\":8,\"0662\":5,\"0724\":1,\"0604\":1,\"0593\":3,\"0539\":4,\"0571\":2,\"0549\":5,\"023\":15,\"0209\":26,\"0886\":2,\"0949\":1,\"0486\":6,\"0341\":4,\"0333\":5,\"0811\":1,\"0415\":2,\"0792\":3,\"0503\":2,\"0381\":1,\"0505\":1,\"0474\":3,\"0261\":23,\"0848\":3,\"0682\":1,\"0537\":3,\"001\":20,\"0467\":3,\"0491\":3,\"0285\":3,\"0296\":5,\"0987\":1,\"0484\":5,\"0575\":4,\"0587\":4,\"0413\":4,\"0376\":4,\"0859\":1,\"0882\":1,\"0676\":3,\"0488\":2,\"0441\":5,\"0275\":10,\"0563\":2,\"0455\":2,\"0527\":5,\"0408\":4,\"0752\":3,\"0899\":1,\"0693\":1,\"0705\":1,\"0598\":3,\"0559\":3,\"0439\":2,\"0789\":2,\"0654\":5,\"0908\":1,\"0747\":1,\"0721\":2,\"0431\":4,\"0632\":2,\"0426\":1,\"0624\":2,\"0485\":3,\"0785\":1,\"0619\":4,\"0448\":3,\"0592\":1,\"0457\":1,\"0375\":5,\"0759\":2,\"0532\":3,\"0545\":5,\"0595\":4,\"0558\":2,\"0297\":6,\"0843\":2,\"0902\":1,\"0768\":2,\"0468\":2,\"0352\":6,\"034\":5,\"033\":6,\"0917\":2,\"0869\":3,\"0888\":2,\"0842\":1,\"0723\":1,\"0701\":1,\"0858\":4,\"0473\":3,\"0384\":1,\"0339\":8,\"0596\":1,\"0276\":8,\"0481\":5,\"0454\":5,\"0435\":2,\"0907\":1,\"0651\":2,\"0411\":5,\"0812\":1,\"0678\":1,\"0954\":1,\"0817\":1,\"0873\":1,\"095\":2,\"0972\":1,\"0815\":1,\"046\":2,\"0621\":3,\"0393\":2,\"0664\":2,\"0809\":2,\"0586\":2,\"0602\":1,\"0237\":17,\"0437\":1,\"0635\":4,\"0516\":1,\"0698\":2,\"0363\":8,\"0629\":3,\"078\":1,\"079\":1,\"0584\":3,\"0687\":5,\"0548\":7,\"0522\":3,\"0576\":2,\"0945\":2,\"0739\":1,\"0667\":1,\"083\":1,\"071\":1,\"0492\":5,\"0803\":1,\"0513\":4,\"0795\":2,\"0709\":1,\"0315\":8,\"0489\":3,\"0349\":6,\"0594\":1,\"0303\":5,\"0976\":1,\"0923\":2,\"0445\":2,\"06\":2,\"0582\":4,\"0346\":5,\"0733\":4,\"0569\":4,\"0826\":1,\"0463\":3,\"0405\":1,\"0708\":1,\"0462\":2,\"0565\":3,\"0521\":6,\"0498\":1,\"0715\":1,\"0573\":1,\"0466\":2,\"0728\":1,\"0658\":2,\"0578\":1,\"042\":1,\"0379\":3,\"067\":4,\"051\":2,\"0329\":4,\"0406\":2,\"0947\":1,\"0656\":5,\"0599\":5,\"0643\":3,\"0324\":6,\"0601\":2,\"0421\":1,\"0518\":3,\"0864\":2,\"0734\":2,\"0627\":3,\"0388\":5,\"0836\":1,\"0177\":10,\"0535\":1,\"0591\":2,\"0394\":4,\"0801\":3,\"0612\":5,\"0423\":4,\"0317\":6,\"0427\":5,\"0707\":2,\"0615\":2,\"072\":1,\"0507\":5,\"0348\":5,\"0552\":3,\"0464\":2,\"0892\":1,\"0971\":1,\"0765\":2,\"0647\":1,\"0685\":1,\"0749\":1,\"0534\":3,\"0397\":3,\"0452\":3,\"0837\":1,\"0404\":3,\"0871\":1,\"0699\":2,\"0444\":2,\"0387\":3,\"0623\":1,\"054\":1,\"0477\":2,\"0378\":1,\"0515\":2,\"0396\":3,\"086\":1,\"0653\":2,\"0881\":2,\"0718\":1,\"056\":1,\"0606\":1,\"0554\":7,\"0302\":7,\"0644\":1,\"04\":1,\"0511\":1,\"0642\":2,\"0761\":1,\"047\":2,\"0401\":1,\"0525\":1,\"0409\":2,\"0744\":2,\"0846\":2,\"0686\":1,\"0579\":4,\"0764\":2,\"0665\":1,\"0555\":3,\"0542\":1,\"0884\":3,\"0696\":1,\"0483\":2,\"0791\":1,\"0741\":1,\"0386\":3,\"064\":1,\"0872\":1,\"0962\":1,\"0862\":1,\"0556\":1,\"0773\":2,\"0533\":3,\"065\":4,\"0419\":1,\"0964\":1,\"0757\":2,\"0422\":2,\"0526\":2,\"0958\":1,\"0865\":2,\"0804\":1,\"0769\":3,\"0506\":1,\"0827\":1,\"0704\":1,\"0906\":1,\"0998\":1,\"094\":1,\"0331\":1,\"0622\":2,\"0877\":1,\"0417\":3,\"0713\":2,\"097\":1,\"0472\":2,\"0469\":2,\"0893\":1,\"035\":2,\"0528\":1,\"044\":1,\"0928\":1,\"0722\":1,\"0471\":2,\"0982\":1,\"0616\":1,\"0551\":2,\"0465\":2,\"0395\":1,\"0613\":1,\"0979\":1,\"073\":1,\"0781\":1,\"0453\":2,\"0916\":1,\"0946\":1,\"0711\":1,\"0935\":1,\"077\":1,\"0889\":2,\"0475\":1,\"093\":1,\"0932\":1,\"0641\":1,\"074\":1,\"0433\":1,\"0557\":1,\"0851\":1,\"0719\":1,\"0903\":1,\"0766\":1,\"0876\":1,\"0775\":2,\"0726\":1,\"0914\":1,\"0633\":1,\"0391\":1,\"0926\":1,\"0867\":1,\"0897\":1,\"0799\":1,\"0767\":1,\"0939\":1,\"0777\":1,\"0997\":1,\"0942\":1,\"0974\":1,\"062\":1,\"0729\":1},\"2\":{\"0\":9198,\"11\":2,\"14\":1,\"15\":1,\"25\":1,\"27\":1,\"104\":2,\"108\":1,\"109\":2,\"111\":1,\"112\":1,\"113\":1,\"114\":1,\"116\":1,\"118\":1,\"121\":2,\"123\":3,\"124\":1,\"138\":2,\"139\":1,\"145\":1,\"146\":1,\"151\":1,\"156\":2,\"159\":1,\"161\":1,\"163\":1,\"165\":1,\"166\":1,\"167\":1,\"174\":1,\"189\":1,\"193\":1,\"205\":1,\"206\":1,\"208\":1,\"219\":1,\"247\":1,\"302\":1,\"306\":1,\"324\":1,\"387\":1,\"446\":1,\"935\":1,\"964\":1,\"1004\":2,\"1011\":1,\"1012\":2,\"1017\":1,\"1018\":2,\"1019\":3,\"1022\":1,\"1026\":2,\"1037\":1,\"1038\":1,\"1042\":2,\"1044\":1,\"1047\":2,\"1049\":1,\"1054\":1,\"1059\":1,\"1064\":1,\"1066\":1,\"1067\":3,\"1068\":1,\"1071\":2,\"1076\":1,\"1077\":1,\"1078\":2,\"1079\":1,\"1082\":1,\"1092\":1,\"1095\":3,\"1099\":1,\"1107\":2,\"1108\":3,\"1115\":2,\"1116\":1,\"1119\":2,\"1122\":1,\"1124\":2,\"1125\":1,\"1126\":1,\"1127\":1,\"1135\":1,\"1137\":1,\"1141\":1,\"1149\":1,\"1153\":1,\"1154\":1,\"1159\":1,\"1167\":2,\"1177\":1,\"1181\":2,\"1182\":1,\"1185\":1,\"1187\":1,\"1193\":1,\"1197\":1,\"1199\":1,\"1201\":3,\"1203\":1,\"1208\":1,\"1209\":1,\"1215\":1,\"1217\":1,\"1218\":1,\"1224\":1,\"1225\":1,\"1238\":1,\"1243\":1,\"1244\":1,\"1245\":1,\"1247\":1,\"1252\":1,\"1257\":1,\"1263\":1,\"1264\":1,\"1266\":1,\"1267\":1,\"1269\":1,\"1274\":1,\"1279\":1,\"1281\":1,\"1282\":1,\"1287\":1,\"1291\":1,\"1292\":2,\"1295\":1,\"1302\":1,\"1303\":1,\"1315\":2,\"1316\":1,\"1325\":2,\"1327\":1,\"1332\":1,\"1335\":1,\"1338\":2,\"1341\":1,\"1342\":1,\"1344\":1,\"1345\":3,\"1348\":1,\"1351\":1,\"1357\":1,\"1363\":1,\"1364\":3,\"1368\":1,\"1373\":1,\"1377\":2,\"1378\":1,\"1381\":1,\"1383\":1,\"1386\":1,\"1388\":1,\"1391\":2,\"1396\":1,\"1401\":2,\"1403\":1,\"1406\":1,\"1408\":1,\"1413\":1,\"1415\":1,\"1422\":1,\"1435\":1,\"1446\":1,\"1453\":1,\"1454\":1,\"1457\":1,\"1461\":2,\"1466\":3,\"1468\":1,\"1472\":1,\"1473\":1,\"1475\":1,\"1479\":1,\"1482\":1,\"1484\":1,\"1487\":1,\"1491\":1,\"1497\":1,\"1499\":1,\"1506\":1,\"1515\":1,\"1521\":1,\"1525\":1,\"1528\":1,\"1533\":1,\"1535\":2,\"1538\":1,\"1541\":1,\"1546\":1,\"1553\":1,\"1554\":1,\"1562\":1,\"1567\":1,\"1571\":2,\"1579\":1,\"1582\":1,\"1583\":1,\"1592\":1,\"1595\":2,\"1596\":1,\"1599\":2,\"1602\":1,\"1605\":1,\"1607\":1,\"1613\":1,\"1618\":1,\"1626\":2,\"1632\":1,\"1635\":1,\"1639\":1,\"1642\":1,\"1665\":1,\"1668\":1,\"1671\":1,\"1672\":1,\"1675\":1,\"1678\":1,\"1679\":1,\"1685\":1,\"1687\":2,\"1688\":1,\"1693\":1,\"1697\":1,\"1701\":2,\"1702\":1,\"1717\":1,\"1719\":1,\"1733\":1,\"1744\":1,\"1748\":1,\"1752\":1,\"1763\":1,\"1769\":2,\"1799\":1,\"1804\":1,\"1805\":1,\"1816\":1,\"1819\":1,\"1836\":1,\"1862\":1,\"1866\":1,\"1871\":1,\"1875\":1,\"1882\":1,\"1883\":1,\"1886\":2,\"1907\":1,\"1908\":1,\"1917\":1,\"1923\":1,\"1933\":1,\"1936\":1,\"1944\":1,\"1957\":1,\"1959\":1,\"1963\":2,\"1968\":1,\"1976\":1,\"2003\":1,\"2014\":1,\"2023\":1,\"2025\":1,\"2029\":1,\"2053\":1,\"2054\":1,\"2057\":1,\"2059\":1,\"2099\":1,\"2125\":1,\"2126\":1,\"2129\":1,\"2134\":1,\"2136\":1,\"2149\":1,\"2162\":1,\"2167\":1,\"2173\":1,\"2182\":2,\"2184\":1,\"2211\":1,\"2221\":1,\"2223\":1,\"2227\":1,\"2233\":1,\"2247\":1,\"2254\":1,\"2257\":1,\"2268\":1,\"2292\":1,\"2298\":1,\"2303\":2,\"2304\":1,\"2312\":1,\"2335\":1,\"2341\":1,\"2356\":1,\"2384\":1,\"2389\":2,\"2405\":1,\"2409\":1,\"2427\":1,\"2473\":1,\"2478\":1,\"2491\":1,\"2502\":2,\"2504\":1,\"2531\":1,\"2557\":1,\"2593\":2,\"2602\":2,\"2619\":1,\"2625\":1,\"2657\":1,\"2668\":1,\"2675\":1,\"2677\":1,\"2689\":1,\"2691\":1,\"2697\":1,\"2721\":1,\"2762\":1,\"2764\":1,\"2848\":1,\"2863\":1,\"2876\":1,\"2958\":1,\"2968\":1,\"2979\":1,\"2987\":1,\"3013\":1,\"3103\":2,\"3137\":1,\"3194\":1,\"3239\":1,\"3293\":1,\"3311\":1,\"3428\":1,\"3447\":1,\"3503\":1,\"3579\":1,\"3709\":1,\"3738\":1,\"3739\":1,\"3821\":1,\"4029\":1,\"4112\":1,\"4261\":1,\"4398\":1,\"4505\":1,\"4626\":1,\"4795\":1,\"5822\":1,\"5957\":1,\"7608\":1,\"7899\":1,\"\":317,\"0294\":5,\"0585\":3,\"0158\":22,\"0364\":5,\"0048\":27,\"0187\":31,\"0033\":28,\"0199\":19,\"0047\":31,\"0155\":24,\"0069\":37,\"0189\":23,\"0086\":33,\"0221\":23,\"0112\":34,\"0249\":22,\"0072\":35,\"0049\":26,\"0002\":22,\"0289\":13,\"0011\":24,\"0195\":17,\"0055\":38,\"0083\":35,\"0065\":33,\"0231\":25,\"0073\":40,\"0181\":17,\"0042\":26,\"0078\":42,\"0213\":21,\"0059\":44,\"0196\":30,\"0157\":26,\"0131\":23,\"047\":4,\"0362\":6,\"0029\":21,\"0261\":13,\"0087\":30,\"0293\":7,\"0084\":32,\"0035\":22,\"0064\":45,\"0172\":24,\"001\":19,\"013\":23,\"0045\":35,\"018\":25,\"0105\":39,\"0032\":14,\"0136\":16,\"0333\":7,\"0624\":2,\"0148\":18,\"0354\":6,\"006\":36,\"0198\":27,\"0102\":30,\"0268\":14,\"0167\":25,\"0103\":31,\"0222\":24,\"0096\":33,\"0142\":26,\"0279\":9,\"004\":19,\"0503\":1,\"0161\":16,\"0367\":5,\"0016\":29,\"0123\":44,\"0044\":34,\"021\":21,\"0106\":33,\"0111\":49,\"0137\":29,\"0119\":38,\"0256\":11,\"0099\":30,\"0043\":29,\"0247\":13,\"0149\":18,\"0057\":49,\"0061\":38,\"0132\":33,\"0297\":6,\"0053\":31,\"011\":37,\"0229\":31,\"008\":42,\"0217\":21,\"0175\":23,\"0162\":24,\"0936\":1,\"0771\":1,\"0817\":2,\"0682\":3,\"061\":4,\"0473\":4,\"0564\":6,\"0347\":10,\"0638\":2,\"0147\":31,\"0353\":11,\"027\":15,\"0085\":40,\"0251\":18,\"0193\":33,\"0115\":43,\"0235\":18,\"0114\":31,\"0248\":15,\"0117\":29,\"0254\":15,\"0037\":41,\"0482\":7,\"0191\":21,\"0067\":30,\"0071\":38,\"0009\":30,\"0025\":27,\"0133\":26,\"0021\":24,\"014\":26,\"0063\":25,\"0315\":18,\"0178\":20,\"0306\":16,\"0269\":11,\"0581\":6,\"0451\":4,\"016\":11,\"0571\":5,\"0365\":14,\"0361\":7,\"0223\":28,\"0426\":4,\"026\":13,\"0396\":8,\"0368\":8,\"031\":9,\"0236\":27,\"0568\":5,\"0166\":26,\"0957\":2,\"0667\":1,\"0726\":3,\"052\":3,\"0788\":3,\"0649\":1,\"0539\":4,\"0373\":7,\"0088\":43,\"0104\":33,\"0224\":19,\"0179\":25,\"0202\":30,\"055\":5,\"03\":7,\"0393\":5,\"0384\":2,\"0245\":26,\"0378\":4,\"0448\":3,\"0328\":7,\"0449\":4,\"0383\":5,\"0246\":30,\"0565\":2,\"0081\":38,\"0075\":37,\"0134\":26,\"0299\":6,\"0007\":26,\"0101\":30,\"0017\":26,\"0244\":14,\"002\":20,\"0156\":17,\"0146\":27,\"0118\":45,\"0934\":1,\"0005\":20,\"0159\":28,\"0461\":3,\"0942\":1,\"0823\":2,\"0715\":2,\"0647\":2,\"0345\":10,\"007\":41,\"0277\":18,\"0127\":20,\"0266\":14,\"0125\":25,\"0089\":30,\"012\":33,\"0255\":10,\"0546\":4,\"0316\":5,\"0201\":30,\"0093\":34,\"0008\":27,\"0128\":27,\"0144\":24,\"096\":1,\"0273\":11,\"0878\":1,\"025\":16,\"054\":5,\"0209\":12,\"0108\":47,\"0274\":14,\"0066\":40,\"0174\":30,\"0074\":31,\"0091\":35,\"0225\":24,\"0276\":19,\"0077\":35,\"0068\":48,\"0963\":1,\"0673\":1,\"0837\":1,\"0631\":1,\"0023\":31,\"0116\":29,\"0019\":27,\"0052\":41,\"0024\":36,\"0186\":21,\"0467\":3,\"045\":3,\"0145\":27,\"0208\":19,\"0034\":18,\"0207\":23,\"0709\":2,\"0543\":3,\"0338\":8,\"023\":24,\"0329\":19,\"0219\":22,\"0971\":3,\"073\":2,\"0499\":2,\"0352\":12,\"0001\":18,\"0113\":31,\"0203\":26,\"0204\":14,\"0129\":19,\"01\":37,\"0537\":6,\"0308\":7,\"0003\":18,\"0206\":22,\"0239\":12,\"0164\":24,\"0371\":7,\"009\":29,\"0092\":42,\"0212\":16,\"0097\":41,\"0232\":12,\"091\":2,\"0619\":4,\"0218\":33,\"0012\":23,\"0854\":3,\"0711\":4,\"0576\":5,\"0326\":9,\"0605\":3,\"0444\":6,\"0258\":21,\"0151\":19,\"0121\":29,\"0253\":23,\"0051\":23,\"0211\":17,\"0153\":19,\"0356\":9,\"0243\":22,\"0169\":18,\"0095\":39,\"0489\":3,\"0291\":10,\"0082\":32,\"0015\":17,\"0107\":35,\"0519\":2,\"0241\":25,\"0283\":11,\"0197\":9,\"0183\":19,\"0474\":3,\"034\":9,\"0026\":23,\"0165\":21,\"0238\":29,\"0336\":5,\"0574\":7,\"0307\":11,\"0079\":40,\"005\":31,\"017\":18,\"0014\":23,\"0041\":38,\"0302\":4,\"0593\":1,\"035\":6,\"0098\":31,\"0264\":10,\"0192\":20,\"0126\":30,\"0139\":33,\"038\":1,\"0062\":37,\"0303\":7,\"0594\":3,\"0325\":6,\"0171\":22,\"0163\":20,\"0036\":22,\"0173\":19,\"0194\":15,\"0185\":13,\"0013\":18,\"0076\":43,\"0184\":19,\"0214\":23,\"0259\":20,\"0054\":23,\"02\":19,\"019\":18,\"0501\":6,\"0281\":8,\"0022\":27,\"0143\":20,\"0046\":32,\"0237\":18,\"0528\":4,\"0141\":26,\"0094\":35,\"0409\":4,\"0058\":39,\"0027\":35,\"0233\":16,\"0343\":10,\"0152\":18,\"0031\":30,\"0267\":13,\"0242\":23,\"0533\":3,\"0109\":39,\"0018\":12,\"033\":4,\"0311\":13,\"0493\":7,\"0177\":17,\"0322\":1,\"0612\":5,\"0359\":8,\"0226\":20,\"0004\":22,\"0028\":24,\"0355\":5,\"0978\":1,\"0687\":1,\"0432\":2,\"0313\":5,\"0607\":3,\"0441\":4,\"049\":2,\"0252\":13,\"0271\":19,\"042\":2,\"0317\":12,\"0168\":23,\"0416\":4,\"0298\":9,\"0749\":1,\"0562\":5,\"0286\":9,\"0965\":2,\"0799\":2,\"0492\":6,\"0765\":1,\"063\":3,\"0428\":2,\"0939\":2,\"0866\":2,\"066\":1,\"0413\":3,\"051\":4,\"0538\":3,\"0319\":6,\"0305\":8,\"0358\":9,\"0648\":3,\"0349\":5,\"0234\":30,\"0801\":3,\"0938\":2,\"0732\":1,\"0787\":1,\"0182\":23,\"0654\":1,\"0469\":4,\"0284\":14,\"0454\":3,\"0915\":1,\"087\":2,\"0979\":3,\"0713\":1,\"0399\":5,\"0135\":16,\"0532\":3,\"0272\":11,\"0176\":29,\"0056\":31,\"0285\":10,\"015\":27,\"0228\":21,\"0536\":2,\"0124\":23,\"0321\":5,\"0611\":2,\"0917\":2,\"0626\":2,\"0309\":14,\"0391\":3,\"0598\":3,\"0521\":6,\"0377\":2,\"0552\":3,\"0526\":3,\"0275\":8,\"028\":16,\"0278\":11,\"0366\":4,\"022\":22,\"0122\":30,\"0516\":4,\"0257\":13,\"0764\":4,\"074\":3,\"0534\":3,\"0475\":4,\"0363\":13,\"0434\":2,\"0138\":15,\"0304\":6,\"0039\":28,\"056\":3,\"0505\":5,\"0265\":10,\"0556\":4,\"0205\":18,\"0453\":2,\"0625\":1,\"0419\":3,\"093\":1,\"0411\":2,\"0844\":1,\"0563\":6,\"0381\":4,\"0955\":3,\"082\":1,\"0987\":2,\"085\":1,\"0459\":3,\"0227\":21,\"0828\":2,\"0369\":5,\"0525\":6,\"0429\":1,\"0507\":3,\"0342\":3,\"0887\":2,\"0681\":1,\"0587\":2,\"0455\":3,\"0566\":2,\"0524\":1,\"0385\":4,\"0877\":1,\"0555\":1,\"0447\":3,\"0845\":1,\"0708\":1,\"0351\":8,\"0216\":16,\"0542\":3,\"0606\":2,\"0372\":5,\"024\":19,\"0671\":2,\"0388\":3,\"0392\":5,\"0334\":5,\"0262\":14,\"0514\":2,\"0357\":4,\"0339\":6,\"0215\":14,\"0498\":5,\"057\":3,\"029\":9,\"0443\":2,\"0829\":1,\"0318\":5,\"0945\":1,\"0811\":1,\"0535\":1,\"0374\":3,\"0548\":3,\"0558\":4,\"0263\":13,\"0415\":5,\"037\":5,\"039\":1,\"0412\":6,\"003\":21,\"0188\":19,\"0331\":8,\"032\":6,\"0038\":28,\"0775\":2,\"0484\":2,\"0382\":3,\"0643\":3,\"0478\":6,\"0154\":24,\"0731\":1,\"0597\":5,\"0954\":2,\"0818\":3,\"071\":3,\"0508\":2,\"0468\":3,\"0736\":1,\"053\":5,\"0422\":1,\"0757\":1,\"062\":2,\"0549\":5,\"0471\":5,\"0403\":3,\"0006\":13,\"0314\":5,\"0604\":2,\"0554\":5,\"0458\":3,\"0421\":3,\"0541\":1,\"0692\":1,\"0402\":2,\"0335\":1,\"0601\":4,\"0506\":2,\"0517\":3,\"0296\":12,\"04\":4,\"05\":4,\"067\":2,\"0662\":2,\"0911\":1,\"0745\":2,\"0798\":1,\"0663\":1,\"0398\":7,\"0495\":1,\"0282\":6,\"0292\":2,\"0969\":1,\"0685\":2,\"0577\":7,\"0436\":5,\"0621\":3,\"0925\":1,\"0806\":1,\"0629\":2,\"0688\":1,\"0737\":1,\"0531\":3,\"0725\":3,\"081\":1,\"0676\":3,\"0839\":1,\"0522\":4,\"0575\":5,\"0295\":6,\"0427\":1,\"0567\":2,\"0504\":1,\"08\":2,\"0705\":2,\"0967\":1,\"0679\":1,\"0646\":1,\"0502\":2,\"036\":7,\"0435\":4,\"0486\":4,\"06\":1,\"0301\":7,\"0497\":4,\"0991\":1,\"0375\":2,\"0941\":1,\"0379\":1,\"0579\":2,\"0512\":4,\"0975\":1,\"0446\":3,\"0405\":1,\"0515\":4,\"059\":3,\"0288\":5,\"0408\":2,\"0758\":1,\"0407\":3,\"0684\":1,\"0518\":1,\"0457\":4,\"0551\":3,\"0465\":2,\"0861\":2,\"0544\":3,\"0962\":1,\"0824\":1,\"0628\":2,\"0923\":1,\"0789\":1,\"0348\":5,\"0312\":7,\"0755\":1,\"0494\":1,\"0561\":1,\"0287\":4,\"0324\":4,\"0615\":2,\"0553\":1,\"041\":3,\"0423\":2,\"0439\":3,\"0513\":2,\"0623\":3,\"0659\":2,\"0937\":1,\"0803\":1,\"0804\":1,\"0488\":3,\"0902\":2,\"0921\":2,\"0816\":3,\"0905\":1,\"0776\":1,\"0586\":2,\"0479\":3,\"0376\":2,\"0608\":1,\"0738\":3,\"0599\":5,\"0706\":1,\"0756\":1,\"0636\":2,\"0401\":2,\"0768\":2,\"0418\":1,\"0914\":1,\"0616\":3,\"0456\":1,\"0859\":1,\"0406\":3,\"0907\":1,\"0639\":1,\"07\":2,\"0337\":5,\"0481\":2,\"0881\":2,\"0723\":1,\"0956\":1,\"079\":1,\"0722\":1,\"0602\":2,\"0769\":1,\"0634\":2,\"0835\":1,\"0462\":3,\"046\":2,\"0791\":2,\"043\":1,\"0346\":4,\"0696\":1,\"0786\":1,\"058\":1,\"0968\":1,\"0802\":2,\"0959\":1,\"0668\":1,\"0596\":2,\"0693\":1,\"0463\":5,\"064\":2,\"0529\":2,\"0841\":1,\"097\":3,\"0812\":1,\"0704\":1,\"0651\":1,\"0658\":2,\"0395\":1,\"0431\":2,\"0919\":1,\"0727\":2,\"0642\":2,\"0694\":2,\"0889\":1,\"0442\":2,\"0864\":1,\"0487\":1,\"0477\":2,\"0438\":1,\"0387\":2,\"0836\":1,\"0632\":1,\"0719\":1,\"0783\":1,\"0592\":4,\"0792\":1,\"0883\":1,\"0466\":1,\"0433\":1,\"0827\":1,\"0832\":2,\"0404\":2,\"0853\":1,\"0716\":1,\"09\":1,\"0472\":2,\"0341\":2,\"0928\":1,\"0896\":2,\"0445\":2,\"0924\":1,\"0993\":1,\"0885\":1,\"0892\":1,\"0898\":1,\"0916\":1,\"0779\":1,\"0509\":2,\"072\":1,\"0617\":1,\"0483\":4,\"0557\":1,\"0595\":1,\"0545\":2,\"0437\":1,\"0981\":2,\"0397\":2,\"0613\":2,\"0344\":2,\"0718\":1,\"0759\":1,\"0935\":1,\"0777\":1,\"0657\":1,\"0742\":1,\"0833\":1,\"0958\":1,\"0752\":1,\"0796\":1,\"0761\":1,\"0485\":2,\"0995\":1,\"0332\":2,\"0523\":2,\"0994\":1,\"0857\":1,\"0728\":1,\"0825\":2,\"0949\":1,\"0988\":1,\"0674\":1,\"0918\":1,\"0943\":1,\"0653\":1,\"0637\":1,\"0763\":1,\"0618\":1,\"0691\":1,\"0697\":1,\"0781\":1,\"0327\":1,\"0809\":1,\"076\":1,\"0655\":2,\"0527\":1,\"088\":1,\"0589\":1,\"048\":1,\"0417\":1,\"0888\":1,\"0622\":1,\"0424\":1,\"0511\":1,\"0496\":1,\"0961\":1},\"3\":{\"0\":6838,\"1\":2,\"104\":1,\"109\":1,\"111\":1,\"113\":1,\"142\":3,\"158\":2,\"197\":1,\"237\":1,\"473\":1,\"1004\":1,\"1011\":1,\"1014\":1,\"1018\":1,\"1021\":2,\"1026\":1,\"1032\":1,\"1037\":1,\"1038\":1,\"1039\":1,\"1042\":1,\"1052\":2,\"1059\":1,\"1064\":1,\"1075\":2,\"1076\":1,\"1077\":1,\"1087\":1,\"1106\":1,\"1107\":1,\"1112\":1,\"1125\":1,\"1133\":1,\"1134\":1,\"1141\":1,\"1142\":1,\"1143\":1,\"1145\":1,\"1146\":1,\"1148\":1,\"1153\":1,\"1155\":1,\"1167\":1,\"1175\":2,\"1178\":1,\"1179\":1,\"1185\":1,\"1186\":1,\"1191\":1,\"1196\":1,\"1204\":1,\"1205\":1,\"1212\":2,\"1214\":1,\"1215\":1,\"1227\":1,\"1241\":1,\"1243\":1,\"1245\":2,\"1251\":1,\"1255\":1,\"1264\":1,\"1267\":1,\"1271\":1,\"1287\":1,\"1289\":1,\"1305\":1,\"1307\":1,\"1308\":2,\"1326\":1,\"1332\":1,\"1341\":1,\"1353\":1,\"1354\":1,\"1375\":1,\"1394\":1,\"1408\":1,\"1409\":1,\"1416\":1,\"1449\":1,\"1457\":1,\"1466\":1,\"1476\":1,\"1477\":1,\"1502\":1,\"1526\":1,\"1531\":1,\"1532\":2,\"1545\":1,\"1554\":1,\"1555\":1,\"1562\":1,\"1594\":1,\"1607\":1,\"1614\":1,\"1644\":1,\"1652\":1,\"1668\":1,\"1683\":1,\"1711\":2,\"1713\":1,\"1719\":1,\"1723\":1,\"1731\":1,\"1756\":1,\"1772\":1,\"1773\":1,\"1806\":1,\"1817\":1,\"1845\":1,\"1879\":1,\"1906\":1,\"1908\":1,\"1931\":1,\"1945\":1,\"2001\":1,\"2013\":1,\"2021\":1,\"2027\":1,\"2079\":1,\"2097\":1,\"2112\":1,\"2137\":1,\"2166\":1,\"2236\":1,\"2247\":1,\"2354\":1,\"2453\":1,\"2603\":1,\"2645\":1,\"2739\":1,\"2967\":1,\"3055\":1,\"3179\":1,\"3258\":1,\"3328\":1,\"3345\":1,\"3356\":1,\"3534\":1,\"4376\":1,\"4439\":1,\"4667\":1,\"5172\":1,\"5326\":1,\"5378\":1,\"5617\":1,\"\":266,\"021\":26,\"05\":2,\"0123\":26,\"0329\":4,\"0121\":17,\"026\":13,\"0118\":30,\"0284\":11,\"0068\":19,\"0176\":17,\"0108\":23,\"0228\":12,\"011\":20,\"0245\":23,\"0034\":27,\"0103\":23,\"0075\":27,\"0086\":38,\"0315\":6,\"0605\":1,\"0165\":13,\"0371\":5,\"0053\":20,\"0192\":17,\"0138\":28,\"0304\":10,\"0099\":37,\"0207\":20,\"0111\":29,\"023\":16,\"0107\":33,\"0242\":16,\"006\":25,\"0197\":21,\"0047\":31,\"005\":30,\"0213\":10,\"0503\":2,\"0131\":18,\"0337\":7,\"013\":23,\"0296\":7,\"0117\":36,\"0224\":15,\"0093\":26,\"0212\":15,\"0061\":19,\"0195\":14,\"0014\":22,\"0151\":11,\"007\":33,\"0079\":28,\"0295\":9,\"0005\":12,\"0358\":4,\"0248\":9,\"0039\":22,\"0205\":21,\"0011\":18,\"0012\":19,\"0148\":14,\"003\":28,\"0167\":10,\"0233\":17,\"0225\":19,\"0229\":19,\"052\":3,\"0065\":33,\"0271\":14,\"0055\":30,\"0194\":19,\"0087\":33,\"0253\":11,\"0006\":19,\"0102\":28,\"002\":19,\"0154\":15,\"0097\":32,\"0234\":14,\"0098\":30,\"0325\":4,\"0616\":2,\"0344\":4,\"0073\":32,\"0274\":13,\"0155\":14,\"0126\":31,\"0246\":19,\"0204\":21,\"0267\":14,\"0051\":40,\"0041\":29,\"0961\":1,\"0821\":2,\"0614\":1,\"0539\":2,\"04\":2,\"0076\":16,\"0089\":28,\"0196\":12,\"0064\":26,\"0729\":3,\"0595\":2,\"0004\":18,\"0133\":15,\"0584\":1,\"0553\":2,\"0332\":6,\"0622\":2,\"0166\":18,\"0372\":4,\"0048\":28,\"0187\":14,\"0135\":13,\"0301\":2,\"0142\":23,\"0114\":37,\"0045\":26,\"018\":14,\"0095\":31,\"0232\":19,\"0057\":18,\"0044\":31,\"0417\":1,\"0361\":3,\"0152\":16,\"0106\":17,\"0272\":15,\"0113\":30,\"0007\":15,\"0182\":15,\"0263\":10,\"0129\":29,\"0419\":1,\"0003\":13,\"0203\":18,\"0172\":11,\"0181\":17,\"0063\":29,\"0132\":17,\"0088\":31,\"0223\":17,\"0513\":1,\"0009\":18,\"0215\":15,\"0112\":33,\"0251\":12,\"01\":18,\"0266\":18,\"0221\":28,\"0231\":13,\"0128\":22,\"0157\":15,\"008\":40,\"034\":5,\"0631\":3,\"0149\":13,\"0355\":7,\"0171\":21,\"014\":23,\"0277\":13,\"0042\":21,\"0036\":20,\"0409\":2,\"0119\":29,\"0308\":5,\"0077\":23,\"0216\":14,\"015\":18,\"0015\":14,\"0054\":29,\"0162\":18,\"0105\":30,\"024\":14,\"0031\":19,\"0264\":10,\"0299\":7,\"0589\":2,\"0163\":22,\"0369\":11,\"0169\":20,\"0069\":25,\"0235\":16,\"0066\":28,\"0173\":13,\"0078\":31,\"0198\":20,\"0019\":22,\"0081\":26,\"0056\":46,\"0294\":10,\"0418\":3,\"0279\":10,\"086\":1,\"0957\":1,\"0464\":2,\"0345\":8,\"0722\":1,\"0588\":3,\"0363\":6,\"0374\":3,\"0083\":28,\"0319\":6,\"0386\":2,\"0278\":14,\"0049\":23,\"0222\":25,\"0037\":20,\"0174\":12,\"0317\":5,\"0259\":13,\"0318\":9,\"0608\":2,\"0145\":14,\"0351\":2,\"0085\":32,\"0059\":31,\"0586\":2,\"0139\":14,\"0072\":28,\"0179\":11,\"0021\":13,\"0141\":20,\"0013\":21,\"0147\":10,\"0188\":20,\"0043\":20,\"0585\":3,\"0261\":11,\"0247\":14,\"0134\":16,\"03\":9,\"0214\":19,\"0239\":13,\"0052\":18,\"028\":18,\"057\":5,\"0316\":3,\"0211\":16,\"0283\":7,\"0238\":14,\"0183\":16,\"0074\":23,\"0403\":2,\"0153\":20,\"0359\":6,\"0084\":19,\"025\":14,\"012\":28,\"0101\":20,\"0497\":5,\"0032\":22,\"0186\":20,\"0109\":29,\"0275\":12,\"0255\":12,\"016\":20,\"0206\":25,\"0033\":27,\"017\":20,\"038\":4,\"0307\":10,\"0094\":21,\"0237\":23,\"0008\":10,\"0607\":3,\"0164\":20,\"037\":6,\"0208\":15,\"0159\":19,\"0125\":20,\"0001\":17,\"0979\":1,\"0689\":3,\"0258\":11,\"022\":19,\"0124\":18,\"0814\":1,\"0677\":2,\"0492\":3,\"0442\":5,\"0839\":1,\"0548\":2,\"0217\":22,\"0298\":4,\"0137\":19,\"0244\":15,\"0393\":2,\"0384\":1,\"0398\":1,\"0127\":27,\"0636\":3,\"047\":1,\"0046\":22,\"0331\":3,\"045\":2,\"0328\":7,\"036\":5,\"0028\":19,\"0175\":13,\"0265\":9,\"0091\":26,\"0022\":19,\"0146\":19,\"0257\":12,\"0547\":3,\"0366\":5,\"001\":24,\"0254\":12,\"0026\":19,\"0058\":32,\"0177\":7,\"0067\":14,\"0201\":15,\"0303\":4,\"0593\":3,\"0339\":3,\"0243\":12,\"0193\":18,\"0082\":20,\"0529\":2,\"0285\":7,\"0161\":17,\"059\":3,\"0023\":18,\"0496\":8,\"0092\":18,\"0226\":9,\"0038\":19,\"0495\":4,\"0199\":14,\"02\":20,\"0143\":13,\"0515\":4,\"0178\":11,\"0024\":16,\"019\":16,\"0122\":27,\"0062\":24,\"0921\":3,\"0322\":6,\"049\":3,\"0252\":14,\"0115\":23,\"0562\":5,\"0016\":20,\"0851\":2,\"0645\":3,\"0327\":6,\"0184\":14,\"0647\":2,\"0541\":3,\"0484\":4,\"0281\":9,\"0312\":11,\"061\":2,\"0334\":7,\"0104\":26,\"0144\":19,\"031\":7,\"0236\":12,\"0249\":16,\"0349\":5,\"064\":2,\"0347\":2,\"0262\":10,\"027\":10,\"004\":20,\"0218\":15,\"0027\":13,\"053\":3,\"0309\":5,\"06\":1,\"0353\":2,\"0644\":2,\"0606\":1,\"0323\":9,\"0619\":3,\"0373\":4,\"0017\":15,\"0136\":20,\"0158\":15,\"0185\":12,\"0025\":18,\"0311\":9,\"0191\":21,\"062\":1,\"0292\":10,\"0333\":5,\"0652\":1,\"0486\":2,\"0471\":3,\"0352\":3,\"035\":7,\"0379\":2,\"0696\":1,\"0545\":4,\"042\":2,\"0168\":13,\"0189\":13,\"0241\":17,\"0096\":22,\"0555\":2,\"0526\":5,\"032\":6,\"0388\":5,\"0604\":2,\"0737\":1,\"0618\":5,\"065\":2,\"0524\":2,\"0269\":16,\"0286\":6,\"0365\":7,\"0071\":23,\"0202\":13,\"0362\":5,\"0653\":1,\"0256\":12,\"0035\":17,\"0427\":3,\"0002\":14,\"0392\":1,\"0682\":1,\"0342\":6,\"0425\":4,\"0306\":7,\"0273\":6,\"0268\":11,\"0406\":2,\"0209\":18,\"0018\":11,\"0731\":1,\"0525\":2,\"0807\":1,\"0668\":1,\"0971\":1,\"0805\":2,\"0395\":1,\"0765\":3,\"0691\":2,\"0592\":1,\"0356\":5,\"0297\":4,\"0575\":2,\"0321\":6,\"0594\":5,\"0227\":15,\"0029\":12,\"009\":19,\"0116\":22,\"0558\":4,\"0975\":1,\"0769\":1,\"0656\":1,\"0536\":1,\"0808\":3,\"033\":5,\"0338\":7,\"0628\":3,\"0219\":13,\"0428\":4,\"0287\":5,\"0571\":4,\"0375\":2,\"0611\":2,\"0282\":8,\"0291\":5,\"0477\":2,\"056\":3,\"0383\":3,\"041\":2,\"029\":5,\"0784\":1,\"0494\":1,\"067\":2,\"0504\":4,\"0466\":2,\"0346\":3,\"0505\":3,\"0354\":2,\"0489\":2,\"0507\":2,\"0603\":1,\"0475\":4,\"0305\":6,\"0156\":18,\"0449\":2,\"0405\":6,\"0738\":1,\"063\":3,\"0736\":3,\"0617\":1,\"0695\":1,\"0568\":2,\"0293\":4,\"0549\":3,\"0599\":2,\"0597\":1,\"0714\":1,\"0574\":3,\"0467\":2,\"0413\":2,\"0843\":2,\"0488\":2,\"0528\":2,\"0493\":2,\"0569\":3,\"0516\":5,\"0314\":6,\"0474\":2,\"0532\":1,\"0336\":4,\"0276\":6,\"051\":1,\"0391\":4,\"097\":1,\"0833\":1,\"0564\":4,\"0559\":3,\"0459\":2,\"0481\":2,\"0453\":1,\"0434\":3,\"0288\":6,\"0578\":2,\"0479\":3,\"0454\":2,\"0302\":9,\"0289\":7,\"0367\":5,\"0657\":1,\"0542\":4,\"0591\":1,\"0326\":5,\"0376\":2,\"0407\":2,\"084\":1,\"043\":2,\"0502\":3,\"0506\":3,\"0396\":2,\"0382\":4,\"0509\":2,\"0364\":6,\"0654\":1,\"0632\":4,\"0512\":8,\"0728\":1,\"0313\":7,\"0439\":2,\"0913\":1,\"0886\":1,\"07\":1,\"0881\":1,\"0761\":2,\"0804\":1,\"0672\":1,\"0624\":3,\"0649\":1,\"0443\":1,\"046\":2,\"0552\":3,\"0341\":4,\"0615\":3,\"0849\":1,\"0733\":1,\"0596\":4,\"0873\":2,\"0811\":1,\"0429\":1,\"0702\":2,\"0893\":1,\"0983\":1,\"0817\":1,\"0853\":1,\"0514\":1,\"0598\":3,\"0567\":2,\"0518\":2,\"0401\":3,\"0543\":1,\"0678\":1,\"0387\":2,\"0397\":2,\"0511\":1,\"0537\":4,\"0437\":1,\"0498\":2,\"0446\":2,\"0457\":2,\"0802\":1,\"0572\":2,\"0438\":1,\"0534\":2,\"0501\":2,\"0522\":1,\"0673\":1,\"0324\":2,\"0587\":4,\"0533\":1,\"0626\":1,\"0565\":3,\"0972\":2,\"0959\":1,\"082\":1,\"0868\":1,\"0703\":1,\"0629\":2,\"0922\":1,\"0785\":2,\"0535\":1,\"0487\":1,\"0412\":3,\"0402\":2,\"0482\":1,\"066\":2,\"0447\":1,\"0508\":2,\"0431\":3,\"0478\":2,\"0378\":2,\"0527\":1,\"0348\":2,\"0422\":1,\"0335\":2,\"0389\":3,\"0966\":1,\"0759\":1,\"0671\":1,\"0499\":4,\"0915\":1,\"0795\":1,\"0823\":1,\"0556\":2,\"0982\":2,\"0658\":1,\"0538\":2,\"0485\":2,\"0715\":1,\"0627\":1,\"0456\":1,\"0566\":2,\"0609\":2,\"0557\":2,\"039\":2,\"0357\":2,\"0472\":2,\"0394\":1,\"0754\":1,\"0546\":1,\"058\":4,\"0958\":1,\"0667\":1,\"0423\":1,\"0517\":1,\"0613\":1,\"0996\":1,\"0938\":1,\"0764\":1,\"0625\":1,\"0414\":1,\"0664\":1,\"0583\":1,\"0634\":1,\"0659\":1,\"0368\":1,\"0424\":1,\"0863\":1,\"0468\":1,\"0455\":1,\"0885\":1,\"0836\":1,\"0461\":1,\"0768\":1,\"0452\":1,\"054\":1,\"0951\":1,\"0483\":1,\"0929\":1,\"0941\":2,\"0581\":1,\"0445\":1,\"0416\":1,\"0612\":1,\"0706\":1,\"0415\":2,\"0411\":1,\"0473\":1,\"048\":1,\"0621\":1,\"0699\":1,\"0408\":1,\"0709\":1,\"071\":1,\"0426\":1,\"0925\":1,\"0973\":1,\"0988\":3,\"088\":1,\"0773\":1,\"0451\":1,\"0858\":1,\"068\":2,\"098\":2,\"0827\":2,\"0708\":2,\"0824\":1,\"0796\":1,\"0576\":2,\"0956\":1,\"075\":1,\"0822\":1,\"0343\":2,\"0852\":1,\"0876\":1,\"0554\":1,\"0633\":3,\"0866\":1,\"0747\":1,\"0663\":1,\"0888\":1,\"0842\":1,\"0707\":1,\"0639\":1,\"0828\":1,\"0841\":1,\"0635\":1,\"0669\":1,\"0573\":1,\"0544\":1,\"0757\":1,\"0441\":1,\"0523\":1,\"0476\":1,\"0641\":1,\"0561\":1,\"0782\":1,\"0772\":1,\"0679\":1},\"4\":{\"0\":7848,\"12\":1,\"14\":2,\"117\":1,\"119\":1,\"123\":1,\"125\":1,\"126\":1,\"128\":1,\"129\":1,\"131\":1,\"137\":1,\"148\":2,\"161\":1,\"176\":1,\"183\":1,\"194\":1,\"207\":1,\"212\":1,\"344\":1,\"1004\":1,\"1009\":1,\"1014\":1,\"1015\":1,\"1018\":1,\"1022\":1,\"1026\":1,\"1033\":1,\"1035\":1,\"1045\":1,\"1051\":2,\"1058\":1,\"1062\":1,\"1069\":1,\"1071\":2,\"1072\":1,\"1081\":1,\"1087\":3,\"1098\":1,\"1114\":1,\"1117\":2,\"1118\":1,\"1141\":2,\"1147\":2,\"1148\":1,\"1161\":1,\"1163\":1,\"1164\":1,\"1174\":1,\"1177\":1,\"1181\":1,\"1183\":2,\"1186\":1,\"1188\":1,\"1195\":1,\"1196\":1,\"1198\":1,\"1207\":1,\"1211\":1,\"1215\":1,\"1218\":1,\"1229\":1,\"1238\":1,\"1248\":1,\"1249\":1,\"1251\":1,\"1257\":1,\"1258\":1,\"1262\":1,\"1266\":1,\"1273\":1,\"1274\":1,\"1281\":1,\"1283\":1,\"1287\":1,\"1302\":1,\"1303\":1,\"1307\":1,\"1314\":1,\"1319\":1,\"1322\":1,\"1325\":2,\"1329\":1,\"1344\":1,\"1348\":1,\"1354\":1,\"1358\":1,\"1361\":1,\"1372\":1,\"1378\":1,\"1386\":1,\"1398\":3,\"1408\":1,\"1426\":2,\"1438\":1,\"1451\":1,\"1456\":1,\"1463\":1,\"1464\":1,\"1474\":1,\"1476\":1,\"1487\":1,\"1498\":1,\"1508\":1,\"1509\":1,\"1523\":1,\"1528\":1,\"1532\":1,\"1536\":1,\"1539\":1,\"1556\":1,\"1564\":1,\"1582\":1,\"1599\":1,\"1639\":1,\"1655\":1,\"1675\":1,\"1683\":1,\"1697\":2,\"1715\":1,\"1725\":1,\"1726\":1,\"1751\":1,\"1763\":1,\"1775\":1,\"1778\":1,\"1788\":1,\"1805\":1,\"1818\":1,\"1821\":1,\"1822\":1,\"1823\":1,\"1824\":1,\"1863\":1,\"1897\":1,\"1903\":2,\"1917\":1,\"1929\":1,\"1932\":1,\"1957\":1,\"1972\":1,\"1984\":1,\"1986\":1,\"1988\":1,\"1994\":1,\"1996\":1,\"2011\":1,\"2027\":1,\"2066\":1,\"2103\":1,\"2115\":1,\"2116\":1,\"2131\":1,\"2277\":1,\"2337\":1,\"2384\":1,\"2389\":1,\"2395\":1,\"2396\":1,\"2465\":1,\"2492\":1,\"2513\":1,\"2523\":1,\"2597\":1,\"2602\":1,\"2614\":1,\"2678\":1,\"2685\":1,\"2711\":1,\"2756\":1,\"2888\":1,\"2905\":1,\"3001\":1,\"3082\":1,\"3149\":1,\"3181\":1,\"3264\":1,\"3353\":1,\"3471\":1,\"3555\":1,\"3643\":1,\"3831\":1,\"3886\":1,\"4121\":1,\"4177\":1,\"4181\":1,\"4387\":1,\"4729\":1,\"4866\":1,\"6268\":1,\"6559\":1,\"\":319,\"0249\":7,\"0539\":6,\"0127\":26,\"0333\":16,\"0066\":38,\"0205\":21,\"0071\":34,\"0237\":34,\"0052\":34,\"016\":24,\"0059\":33,\"0178\":21,\"0013\":10,\"0147\":16,\"0025\":18,\"0162\":20,\"0095\":29,\"005\":32,\"024\":20,\"0181\":27,\"01\":32,\"0238\":17,\"0026\":24,\"0192\":13,\"009\":25,\"0198\":22,\"0049\":31,\"0051\":25,\"0186\":17,\"0107\":34,\"0244\":28,\"0153\":14,\"0324\":3,\"0614\":4,\"0368\":5,\"0189\":20,\"0068\":39,\"0234\":11,\"0203\":22,\"0065\":26,\"0185\":17,\"0108\":47,\"0242\":22,\"0142\":22,\"0278\":17,\"0047\":34,\"0391\":1,\"0231\":27,\"0075\":27,\"0214\":25,\"0144\":30,\"0309\":11,\"004\":28,\"0079\":32,\"0199\":20,\"0184\":15,\"0038\":30,\"0175\":14,\"0119\":34,\"0105\":34,\"0533\":2,\"0313\":7,\"0097\":35,\"0235\":16,\"0285\":13,\"008\":33,\"0187\":19,\"0015\":16,\"0135\":28,\"0114\":29,\"0248\":23,\"0133\":26,\"027\":17,\"0283\":8,\"0573\":4,\"0121\":21,\"0287\":6,\"0091\":35,\"006\":31,\"018\":14,\"0084\":17,\"0218\":20,\"0012\":18,\"0125\":31,\"0078\":34,\"0058\":43,\"0196\":19,\"0487\":1,\"0271\":8,\"0152\":16,\"0128\":21,\"0294\":5,\"0007\":21,\"0113\":37,\"0103\":46,\"0163\":28,\"0426\":1,\"0061\":40,\"0145\":21,\"0225\":24,\"0093\":38,\"0201\":17,\"0083\":33,\"0217\":22,\"0123\":24,\"026\":15,\"0112\":33,\"0111\":27,\"0288\":5,\"0578\":2,\"0164\":24,\"037\":9,\"0035\":22,\"0174\":17,\"0138\":18,\"0304\":2,\"0064\":36,\"0042\":35,\"0179\":15,\"0056\":26,\"0336\":8,\"0627\":2,\"0224\":26,\"0166\":25,\"0117\":39,\"0236\":19,\"019\":24,\"007\":27,\"0282\":6,\"0129\":22,\"0335\":6,\"0197\":23,\"0074\":39,\"0009\":20,\"0232\":14,\"0208\":19,\"0314\":6,\"0605\":6,\"0262\":12,\"0291\":7,\"0099\":27,\"0207\":22,\"0239\":21,\"0126\":34,\"0263\":21,\"0039\":28,\"0046\":40,\"0053\":27,\"0343\":4,\"0054\":32,\"0024\":22,\"014\":26,\"0306\":16,\"0069\":31,\"001\":17,\"013\":25,\"0193\":16,\"0148\":16,\"0257\":9,\"0547\":3,\"0149\":16,\"0355\":6,\"0027\":18,\"0226\":21,\"0006\":22,\"0131\":16,\"0088\":33,\"0245\":19,\"0922\":2,\"0863\":1,\"0073\":37,\"0363\":6,\"0318\":7,\"0036\":29,\"0104\":40,\"0062\":40,\"0003\":18,\"0115\":21,\"0031\":22,\"0004\":15,\"0302\":7,\"0593\":3,\"0143\":21,\"0349\":5,\"0081\":47,\"022\":23,\"0118\":43,\"0284\":13,\"0157\":14,\"0085\":24,\"0204\":15,\"0086\":31,\"0221\":22,\"0094\":30,\"0043\":22,\"0303\":9,\"0048\":31,\"0077\":35,\"0254\":15,\"0544\":3,\"035\":9,\"0076\":31,\"0219\":18,\"0018\":24,\"0155\":13,\"0008\":18,\"0158\":17,\"0033\":23,\"0029\":20,\"0267\":8,\"0227\":23,\"0517\":1,\"011\":21,\"0316\":3,\"0063\":35,\"0202\":21,\"0096\":43,\"0005\":18,\"0132\":22,\"0597\":6,\"0122\":22,\"0261\":12,\"0102\":34,\"0268\":14,\"0168\":22,\"0243\":22,\"0183\":21,\"0724\":1,\"0943\":1,\"0737\":3,\"0222\":26,\"0305\":11,\"0437\":3,\"0329\":6,\"0473\":1,\"0354\":5,\"0034\":25,\"0527\":2,\"0496\":3,\"0534\":4,\"0194\":13,\"0055\":25,\"0255\":19,\"0515\":4,\"0028\":15,\"0412\":1,\"0032\":22,\"015\":13,\"0092\":36,\"0574\":2,\"0366\":3,\"0106\":27,\"0272\":15,\"0087\":31,\"0269\":9,\"056\":1,\"0351\":4,\"0137\":27,\"0173\":22,\"0246\":18,\"0209\":19,\"0089\":26,\"0057\":31,\"0581\":2,\"0159\":17,\"0365\":9,\"0041\":37,\"0109\":38,\"0275\":8,\"003\":17,\"0206\":13,\"0223\":20,\"0161\":19,\"0253\":12,\"0228\":14,\"0419\":4,\"0067\":31,\"0274\":20,\"0022\":21,\"094\":1,\"0745\":1,\"0384\":4,\"0738\":1,\"0572\":1,\"0292\":14,\"0321\":6,\"0524\":2,\"039\":1,\"025\":10,\"0739\":2,\"041\":2,\"0215\":22,\"0216\":21,\"0295\":9,\"0585\":2,\"0154\":26,\"0281\":9,\"0566\":5,\"0044\":29,\"021\":16,\"028\":9,\"0311\":8,\"0172\":14,\"0812\":1,\"0646\":1,\"0917\":2,\"0809\":2,\"0382\":1,\"0247\":13,\"0826\":1,\"0689\":1,\"0557\":3,\"0339\":5,\"0141\":32,\"0307\":13,\"0583\":3,\"0359\":3,\"023\":14,\"0014\":16,\"02\":22,\"0124\":25,\"0323\":7,\"0098\":26,\"0019\":11,\"0101\":29,\"0298\":16,\"0589\":6,\"0212\":29,\"044\":1,\"0165\":16,\"0371\":10,\"0072\":30,\"012\":21,\"0229\":28,\"0519\":2,\"0176\":15,\"0367\":5,\"0876\":2,\"0301\":8,\"0592\":4,\"0344\":2,\"029\":5,\"0211\":23,\"0251\":11,\"0542\":4,\"0233\":25,\"0432\":1,\"0182\":14,\"0466\":3,\"0045\":29,\"0134\":13,\"0213\":24,\"0492\":2,\"0156\":19,\"0362\":9,\"0241\":24,\"0411\":2,\"0002\":17,\"0296\":13,\"0561\":3,\"0195\":18,\"0082\":31,\"0735\":1,\"0707\":2,\"0501\":2,\"0397\":2,\"0289\":5,\"0415\":4,\"0429\":2,\"0315\":7,\"033\":3,\"0177\":9,\"0273\":11,\"0564\":2,\"0151\":23,\"0512\":2,\"0364\":5,\"031\":12,\"0146\":14,\"0576\":4,\"0325\":9,\"0171\":10,\"017\":9,\"0886\":1,\"0595\":3,\"0252\":21,\"0395\":2,\"0525\":2,\"0417\":5,\"0451\":2,\"0389\":6,\"0484\":2,\"0264\":10,\"0256\":13,\"0535\":5,\"0136\":18,\"0427\":1,\"0266\":8,\"0562\":5,\"0425\":3,\"0016\":12,\"0462\":2,\"0973\":1,\"0682\":1,\"0479\":1,\"0794\":1,\"0655\":1,\"0744\":1,\"0472\":3,\"0499\":2,\"0741\":1,\"0337\":6,\"0327\":5,\"0618\":3,\"0346\":6,\"0011\":16,\"0454\":1,\"0191\":20,\"0435\":2,\"0579\":2,\"058\":3,\"0299\":5,\"002\":9,\"0017\":18,\"0616\":2,\"036\":9,\"0116\":37,\"0169\":12,\"0338\":5,\"0908\":1,\"0664\":1,\"0457\":1,\"0023\":21,\"0528\":3,\"0819\":2,\"0348\":5,\"0599\":3,\"0334\":5,\"0625\":1,\"0548\":1,\"0167\":19,\"0139\":18,\"0276\":7,\"0587\":4,\"0558\":2,\"0347\":5,\"0637\":1,\"0356\":7,\"0279\":9,\"057\":4,\"034\":6,\"063\":1,\"0372\":2,\"0293\":11,\"0258\":11,\"0265\":5,\"0554\":3,\"0308\":7,\"0328\":7,\"0531\":2,\"0021\":16,\"0604\":4,\"03\":5,\"0523\":2,\"0545\":2,\"0357\":5,\"0188\":21,\"0286\":3,\"0424\":1,\"0259\":15,\"0888\":1,\"0465\":2,\"0456\":2,\"0001\":17,\"0537\":4,\"0594\":3,\"064\":3,\"0037\":18,\"0954\":3,\"0815\":1,\"0905\":1,\"0379\":2,\"0502\":3,\"0761\":1,\"0353\":6,\"0504\":2,\"0601\":3,\"0352\":5,\"0522\":3,\"032\":8,\"0374\":9,\"0388\":2,\"05\":2,\"0514\":3,\"0491\":3,\"0405\":2,\"0439\":2,\"0626\":3,\"0277\":9,\"0331\":6,\"0342\":4,\"0633\":3,\"054\":1,\"0341\":9,\"0463\":2,\"0317\":5,\"0387\":2,\"0332\":6,\"0787\":1,\"0549\":3,\"0653\":1,\"0326\":3,\"0617\":2,\"0392\":2,\"0623\":4,\"0478\":1,\"0831\":1,\"0693\":1,\"0698\":1,\"059\":3,\"0672\":1,\"0418\":2,\"06\":1,\"0632\":3,\"0375\":1,\"0665\":3,\"0312\":10,\"0861\":2,\"0727\":1,\"069\":2,\"0431\":1,\"0438\":2,\"0829\":1,\"0932\":1,\"0834\":1,\"0668\":2,\"0914\":1,\"0985\":1,\"0865\":1,\"0851\":1,\"0714\":1,\"0538\":4,\"0361\":6,\"0445\":4,\"0788\":1,\"0498\":3,\"0647\":2,\"0481\":3,\"0319\":5,\"049\":2,\"0567\":4,\"0446\":1,\"0678\":2,\"0345\":8,\"0584\":2,\"0476\":1,\"0369\":6,\"0964\":1,\"0758\":1,\"0516\":2,\"0377\":3,\"0428\":1,\"0767\":1,\"0493\":2,\"0297\":8,\"0588\":4,\"0536\":2,\"0452\":1,\"0571\":2,\"0322\":4,\"0563\":2,\"0489\":1,\"0892\":2,\"0856\":1,\"0748\":2,\"0953\":1,\"095\":1,\"0909\":1,\"0381\":3,\"0408\":2,\"0546\":1,\"0475\":2,\"052\":1,\"0503\":3,\"0575\":1,\"0636\":2,\"0608\":2,\"0464\":3,\"0569\":2,\"051\":1,\"0409\":1,\"0765\":1,\"0631\":3,\"042\":1,\"0857\":1,\"0772\":1,\"0541\":2,\"0376\":2,\"0413\":1,\"0543\":2,\"0551\":4,\"0622\":3,\"0997\":1,\"043\":3,\"0401\":2,\"0373\":4,\"0393\":2,\"0529\":2,\"0396\":2,\"0603\":3,\"0612\":2,\"0555\":3,\"0774\":1,\"0483\":1,\"0447\":2,\"0641\":1,\"0613\":2,\"0844\":1,\"0715\":1,\"0979\":1,\"0789\":1,\"047\":2,\"08\":2,\"068\":1,\"0677\":2,\"0752\":1,\"0929\":1,\"0795\":1,\"0609\":2,\"0793\":1,\"046\":3,\"077\":1,\"048\":2,\"0402\":2,\"0723\":1,\"0553\":4,\"0422\":1,\"055\":2,\"0969\":1,\"0679\":2,\"0673\":1,\"0666\":1,\"045\":1,\"0488\":2,\"0506\":1,\"0358\":4,\"0686\":1,\"0459\":1,\"0634\":1,\"0513\":4,\"0645\":1,\"0684\":1,\"0394\":1,\"0441\":1,\"0842\":1,\"0705\":1,\"0924\":1,\"0552\":1,\"053\":1,\"0768\":1,\"0518\":2,\"0467\":1,\"0444\":2,\"0889\":1,\"0755\":1,\"0403\":2,\"0621\":1,\"0586\":2,\"0998\":1,\"0385\":1,\"0982\":1,\"061\":2,\"0611\":2,\"0508\":2,\"0651\":1,\"04\":1,\"0951\":1,\"0669\":1,\"0781\":1,\"0526\":1,\"0458\":1,\"0642\":1,\"0482\":3,\"0521\":3,\"0511\":1,\"0871\":1,\"0903\":1,\"0598\":1,\"0448\":1,\"0398\":1,\"0596\":1,\"0602\":1,\"075\":1,\"0993\":1,\"0702\":1,\"0495\":1,\"0628\":1,\"0746\":1,\"0468\":1,\"0797\":2,\"0663\":2,\"0662\":1,\"0455\":1,\"0796\":1,\"0688\":1,\"0899\":2,\"0777\":1,\"0532\":1,\"087\":1,\"0722\":1,\"0726\":1,\"0814\":1,\"0837\":1,\"0717\":1,\"0747\":1,\"0824\":1,\"0687\":1,\"0474\":1,\"0606\":1,\"0657\":1,\"0661\":1,\"0885\":1,\"0703\":1}},\"options\":{}}","trainAccuracy":0,"testAccuracy":0.4803675856307435,"preProcess":{"stats":{"normalizationFeat":[{"min":184,"max":3731916},{"min":174,"max":1080117},{"min":14,"max":306923},{"min":64,"max":262817},{"min":126,"max":584674},{"min":208,"max":199913},{"min":52,"max":166988},{"min":28,"max":537534}],"devMatrix":{"gralMean":null,"gralStd":null,"featureStats":[{"feature":"delta","mean":0.04682820290327072,"variance":0.005759837571531534,"std":0.0758935958147049},{"feature":"theta","mean":0.016826773062348366,"variance":0.0014019557274878025,"std":0.03744269907474518},{"feature":"lowAlpha","mean":0.013392060995101929,"variance":0.0007438432076014578,"std":0.02727348916232586},{"feature":"highAlpha","mean":0.014713856391608715,"variance":0.0009797335369512439,"std":0.03130069375038147},{"feature":"lowBeta","mean":0.011754017323255539,"variance":0.0005074476939626038,"std":0.02252659946680069},{"feature":"highBeta","mean":0.012614113278687,"variance":0.0006036316626705229,"std":0.024568917229771614},{"feature":"lowGamma","mean":0.01187499612569809,"variance":0.0006403235602192581,"std":0.02530461549758911},{"feature":"highGamma","mean":0.014472258277237415,"variance":0.000793141545727849,"std":0.028162768110632896}]},"filter":[{"min":0,"max":1,"mean":0.03949924185872078,"std":0.09724611043930054,"q1":0.0012182011269032955,"median":0.004133469425141811,"q3":0.023858893662691116},{"min":0,"max":1,"mean":0.027113083750009537,"std":0.05703302100300789,"q1":0.00407336326315999,"median":0.008956028148531914,"q3":0.025205034762620926},{"min":0,"max":1,"mean":0.03102521412074566,"std":0.05493391305208206,"q1":0.007484303321689367,"median":0.015017480589449406,"q3":0.03024023398756981},{"min":0,"max":1,"mean":0.0298027154058218,"std":0.049989815801382065,"q1":0.009122636169195175,"median":0.015889447182416916,"q3":0.02893592044711113},{"min":0,"max":1,"mean":0.011318517848849297,"std":0.024649742990732193,"q1":0.0037995169404894114,"median":0.00605425052344799,"q3":0.010242101736366749},{"min":0,"max":1,"mean":0.022091230377554893,"std":0.03793074190616608,"q1":0.007671315222978592,"median":0.011832453310489655,"q3":0.020244861021637917},{"min":0,"max":1,"mean":0.010861044749617577,"std":0.03698540851473808,"q1":0.0029232760425657034,"median":0.004558633081614971,"q3":0.00817678589373827},{"min":0,"max":1,"mean":0.015601756051182747,"std":0.0559900663793087,"q1":0.0011962656863033772,"median":0.003358101937919855,"q3":0.01332822348922491}]},"trainingSettings":{"selectedFeatures":["delta_m","delta_std","theta_m","theta_std","lowAlpha_m","lowAlpha_std","highAlpha_m","highAlpha_std","lowBeta_m","lowBeta_std","highBeta_m","highBeta_std","lowGamma_m","lowGamma_std","highGamma_m","highGamma_std","mean","std"],"truncateDecimals":4,"classRemap":true,"fourier":true,"normalization":true,"dataAugmentation":false,"deviationMatrix":true,"truncate":true}},"featureNames":["delta_m","delta_std","theta_m","theta_std","lowAlpha_m","lowAlpha_std","highAlpha_m","highAlpha_std","lowBeta_m","lowBeta_std","highBeta_m","highBeta_std","lowGamma_m","lowGamma_std","highGamma_m","highGamma_std","mean","std"],"options":null}